Workbook
Name ModelStart: 'Inputs'!$C$7
Name CapPrice: 'Inputs'!$C$8
Name PriceEsc: 'Inputs'!$C$9
Name OMEsc: 'Inputs'!$C$10
Name Contingency: 'Inputs'!$C$11
Name Insurance: 'Inputs'!$C$12
Name PropTax: 'Inputs'!$C$13
Name GACost: 'Inputs'!$C$14
Name TaxRate: 'Inputs'!$C$15
Name ITCRate: 'Inputs'!$C$16
Name ITCTransfer: 'Inputs'!$C$17
Name ITCBasisRed: 'Inputs'!$C$18
Name SrRateBase: 'Inputs'!$C$22
Name SrDSCR: 'Inputs'!$C$23
Name SrMaxGear: 'Inputs'!$C$24
Name SrFee: 'Inputs'!$C$25
Name MzRateBase: 'Inputs'!$C$26
Name CombDSCR: 'Inputs'!$C$27
Name TotMaxGear: 'Inputs'!$C$28
Name MzFee: 'Inputs'!$C$29
Name Tenor: 'Inputs'!$C$30
Name CostEquity: 'Inputs'!$C$31
Name TotalCapexInputs: 'Inputs'!$T$40
Name MACRS_5: 'Inputs'!$C$45:$C$60
Name MACRS_15: 'Inputs'!$D$45:$D$60
Name ScenarioSel: 'Scenarios'!$C$5
Name CapexAdj: 'Scenarios'!$H$9
Name PriceAdj: 'Scenarios'!$H$10
Name Delay: 'Scenarios'!$H$11
Name RateAdj: 'Scenarios'!$H$12
Name OMAdj: 'Scenarios'!$H$13
Name TotalCapex: 'Annual'!$C$20
Name ConvYear: 'Annual'!$C$30
Name SrRate: 'Annual'!$C$31
Name MzRate: 'Annual'!$C$32
Name SrAmt: 'Annual'!$C$43
Name MzAmt: 'Annual'!$C$56
Name EqIRR: 'Summary'!$C$8
Name CostEquityOut: 'Summary'!$C$9
Name ProjIRR: 'Summary'!$C$10
Name WACC: 'Summary'!$C$11
Name ProjNPV: 'Summary'!$C$12
Name EqNPV: 'Summary'!$C$13
Name Payback: 'Summary'!$C$14
Name MinDSCRSr: 'Summary'!$C$23
Name AvgDSCRSr: 'Summary'!$C$24
Name MinDSCRComb: 'Summary'!$C$25
Name Gearing: 'Summary'!$C$26
Name ConvYearOut: 'Summary'!$C$27
Name RequiredPrice: 'Scenarios'!$O$10

Sheet Cover
B2: Battery Storage Project Finance & Capacity Pricing Model
B3: Portfolio of front-of-the-meter battery storage and backup generation assets · Kshama Upadhyay
B5: Purpose | C5: Value a 400 MW portfolio (four BESS sites + one backup generation site), size a senior/mezzanine/equity capital stack, and solve for the capacity price that delivers the sponsor's target equity IRR.
B6: Status | C6: All assumptions are illustrative and logged in 'Assumption Log' with an owner and a validation source. Not investment advice.
B7: Units | C7: Nominal USD, $ thousands ($k) unless stated. Monthly operating timeline Jan-2027 to Dec-2049; financing and returns annual.
B9: Sheet guide
B10: Summary | C10: Returns, capital stack, required capacity price, debt metrics, charts.
B11: Inputs | C11: General, market, tax and financing assumptions, asset-level table, MACRS tables.
B12: Scenarios | C12: Active-case selector (Base / Downside / Upside), sensitivity flex cells, Excel Data Tables, required-price solver.
B13: Monthly | C13: Asset-level operating flags, degradation, revenue, opex and construction capex by month.
B14: Annual | C14: Annual roll-up, ITC, MACRS depreciation, sculpted senior and mezz debt, tax, project and equity cash flows.
B15: Assumption Log | C15: Every input with owner, basis and validation source; values link live to Inputs.
B16: Checks | C16: Integrity checks (debt repaid, DSCR floors, sources = uses, monthly-to-annual tie-outs).
B18: Conventions | C18: Blue on yellow = hard-coded input · black = formula · green = link to another sheet. No hard-codes in calculation sheets.
B19: Methodology | C19: Debt is sized at term conversion (latest COD) by sculpting debt service to CFADS / target DSCR, capped by gearing. Mezzanine takes the gap between the senior and combined DSCR targets. CFADS for sizing is pre-tax EBITDA (no circularity). Storage ITC is monetized by transfer the year after COD. Tax losses are assumed usable by the sponsor.
B20: How to re-solve price | C20: Scenarios!O10 updates automatically on recalc. Or use Data → What-If Analysis → Goal Seek: set Summary!C8 (Equity IRR) to the target by changing Inputs!CapPrice.
B21: Recalculation | C21: If Data Tables look stale, press F9 (or set Formulas → Calculation Options → Automatic).

Sheet Summary
B2: Battery Storage Portfolio — Project Finance Summary
B3: Front-of-the-meter storage + backup generation. Live outputs for the active scenario. $k unless stated.
B5: Active scenario | C5: =Scenarios!D5 | E5: Model checks | F5: =IF(Checks!C4,"ALL OK","CHECK ERRORS")
B7: Returns & valuation | E7: Sources & uses at term conversion
B8: Equity IRR (levered, after-tax) | C8: =IRR(Annual!$E$75:$AA$75) | F8: $k | G8: % total
B9: Target equity IRR | C9: =CostEquity | E9: Senior debt | F9: =SrAmt | G9: =F9/$F$12
B10: Project IRR (unlevered, after-tax) | C10: =IRR(Annual!$E$74:$AA$74) | E10: Mezzanine debt | F10: =MzAmt | G10: =F10/$F$12
B11: WACC (discount rate for project NPV) | C11: =(SrAmt*SrRate*(1-TaxRate)+MzAmt*MzRate*(1-TaxRate)+(TotalCapex-SrAmt-MzAmt)*CostEquity)/TotalCapex | E11: Sponsor equity | F11: =TotalCapex-SrAmt-MzAmt | G11: =F11/$F$12
B12: Project NPV @ WACC | C12: =NPV(WACC,Annual!$E$74:$AA$74) | E12: Total sources | F12: =SUM(F9:F11) | G12: =SUM(G9:G11)
B13: Equity NPV @ cost of equity | C13: =NPV(CostEquity,Annual!$E$75:$AA$75) | E13: Total capex (uses) | F13: =TotalCapex
B14: Equity payback year (cumulative ≥ 0) | C14: =IFERROR(INDEX(Annual!$E$5:$AA$5,MATCH(TRUE,INDEX(Annual!$E$76:$AA$76>=0,0),0)),"n/a") | E14: ITC cash (transfer, post-COD) | F14: =Annual!D21
E15: Upfront financing fees (equity-funded) | F15: =Annual!D64
B16: Capacity pricing
B17: Capacity price in live case ($/kW-month, 2027 $) | C17: =CapPrice*(1+PriceAdj) | E17: Portfolio
B18: Required price for target equity IRR | C18: =RequiredPrice | E18: Asset | F18: MW | G18: MWh | H18: Capex $k | I18: Live COD
B19: Headroom vs. required price | C19: =IFERROR(C17/C18-1,"n/a") | E19: =Inputs!B35&" ("&Inputs!C35&")" | F19: =Inputs!D35 | G19: =Inputs!S35 | H19: =Inputs!T35 | I19: =Inputs!U35
B20: Required price is interpolated from the Scenarios solver table; Goal Seek EqIRR → CostEquity by changing Inputs!CapPrice gives the same answer. | E20: =Inputs!B36&" ("&Inputs!C36&")" | F20: =Inputs!D36 | G20: =Inputs!S36 | H20: =Inputs!T36 | I20: =Inputs!U36
E21: =Inputs!B37&" ("&Inputs!C37&")" | F21: =Inputs!D37 | G21: =Inputs!S37 | H21: =Inputs!T37 | I21: =Inputs!U37
B22: Debt metrics | E22: =Inputs!B38&" ("&Inputs!C38&")" | F22: =Inputs!D38 | G22: =Inputs!S38 | H22: =Inputs!T38 | I22: =Inputs!U38
B23: Minimum senior DSCR | C23: =MIN(Annual!$E$65:$AA$65) | E23: =Inputs!B39&" ("&Inputs!C39&")" | F23: =Inputs!D39 | G23: =Inputs!S39 | H23: =Inputs!T39 | I23: =Inputs!U39
B24: Average senior DSCR | C24: =AVERAGE(Annual!$E$65:$AA$65) | E24: Total | F24: =SUM(F19:F23) | G24: =SUM(G19:G23) | H24: =SUM(H19:H23)
B25: Minimum combined DSCR | C25: =MIN(Annual!$E$66:$AA$66)
B26: Total gearing (debt / capex) | C26: =(SrAmt+MzAmt)/TotalCapex
B27: Term conversion year | C27: =ConvYear

Sheet Inputs
B2: Inputs
B3: Blue cells on yellow are inputs. Black cells are formulas. $ figures in thousands ($k) unless stated.
B5: General & market
B6: Assumption | C6: Value | D6: Unit | E6: Note
B7: Model start / valuation date | C7: 46388 | D7: date | E7: Monthly timeline starts here; NPVs are discounted to this date
B8: Capacity price (2027 $) | C8: 11 | D8: $/kW-month | E8: Paid on accredited MW. Use Goal Seek or Scenarios!required price to back-solve
B9: Capacity price & margin escalation | C9: 0.02 | D9: % / yr
B10: O&M, lease & G&A escalation | C10: 0.025 | D10: % / yr
B11: Owner's costs & contingency | C11: 0.05 | D11: % of EPC | E11: Applied on top of EPC unit costs
B12: Insurance | C12: 0.004 | D12: % capex / yr
B13: Property tax | C13: 0.005 | D13: % capex / yr
B14: Portfolio G&A and asset management | C14: 1000 | D14: $k / yr | E14: Starts at first COD, escalates with O&M
B15: Blended income tax rate | C15: 0.26 | D15: % | E15: Losses assumed usable by sponsor (negative tax = benefit)
B16: Investment tax credit (storage only) | C16: 0.3 | D16: % eligible capex | E16: Monetized via transfer; cash received the year after COD
B17: ITC transfer price | C17: 0.92 | D17: $ per $1 credit
B18: Depreciable basis reduction | C18: 0.5 | D18: % of ITC
B20: Financing
B21: Assumption | C21: Value | D21: Unit | E21: Note
B22: Senior debt interest rate | C22: 0.065 | D22: % / yr | E22: Live rate adds Scenarios rate adjustment
B23: Senior target DSCR | C23: 1.35 | D23: x | E23: Debt service sculpted to CFADS / target DSCR
B24: Senior max gearing | C24: 0.6 | D24: % of capex | E24: Cap on senior sizing
B25: Senior upfront fee | C25: 0.015 | D25: % of amount
B26: Mezzanine interest rate | C26: 0.105 | D26: % / yr
B27: Combined (senior + mezz) target DSCR | C27: 1.2 | D27: x | E27: Mezz takes the gap between senior and combined DSCR
B28: Total max gearing | C28: 0.75 | D28: % of capex
B29: Mezzanine upfront fee | C29: 0.02 | D29: % of amount
B30: Debt tenor (both tranches) | C30: 15 | D30: years | E30: From term conversion (latest COD)
B31: Cost of equity / target equity IRR | C31: 0.11 | D31: % | E31: Hurdle for required capacity price
B33: Asset portfolio | R33: Calculated (do not edit) →
B34: Asset | C34: Technology | D34: MW | E34: Duration (h) | F34: EPC unit cost | G34: Cost unit | H34: Build (months) | I34: COD (base) | J34: Capacity accreditation | K34: Degradation / yr | L34: Fixed O&M $/kW-yr | M34: Energy & ancillary margin $/kW-yr | N34: Site lease $k/yr | O34: ITC eligible (1/0) | P34: MACRS life (5/15) | Q34: Useful life (yrs) | R34: $/kW (EPC) | S34: MWh | T34: Total capex $k | U34: COD (live, incl. delay) | V34: COD year | W34: Capex start | X34: ITC $k | Y34: Tax basis $k | Z34: Life end
B35: Alpha | C35: BESS | D35: 100 | E35: 4 | F35: 330 | G35: $/kWh | H35: 11 | I35: 46722 | J35: 0.9 | K35: 0.02 | L35: 28 | M35: 45 | N35: 150 | O35: 1 | P35: 5 | Q35: 20 | R35: =F35*IF(G35="$/kWh",E35,1) | S35: =D35*E35 | T35: =D35*R35*(1+Contingency)*(1+CapexAdj) | U35: =EDATE(I35,Delay) | V35: =YEAR(U35) | W35: =EDATE(I35,-H35) | X35: =T35*ITCRate*O35 | Y35: =T35*(1-ITCBasisRed*ITCRate*O35) | Z35: =EDATE(U35,12*Q35)
B36: Bravo | C36: BESS | D36: 75 | E36: 4 | F36: 335 | G36: $/kWh | H36: 12 | I36: 46753 | J36: 0.9 | K36: 0.02 | L36: 28 | M36: 45 | N36: 120 | O36: 1 | P36: 5 | Q36: 20 | R36: =F36*IF(G36="$/kWh",E36,1) | S36: =D36*E36 | T36: =D36*R36*(1+Contingency)*(1+CapexAdj) | U36: =EDATE(I36,Delay) | V36: =YEAR(U36) | W36: =EDATE(I36,-H36) | X36: =T36*ITCRate*O36 | Y36: =T36*(1-ITCBasisRed*ITCRate*O36) | Z36: =EDATE(U36,12*Q36)
B37: Charlie | C37: BESS | D37: 50 | E37: 2 | F37: 390 | G37: $/kWh | H37: 9 | I37: 46844 | J37: 0.6 | K37: 0.025 | L37: 24 | M37: 35 | N37: 90 | O37: 1 | P37: 5 | Q37: 20 | R37: =F37*IF(G37="$/kWh",E37,1) | S37: =D37*E37 | T37: =D37*R37*(1+Contingency)*(1+CapexAdj) | U37: =EDATE(I37,Delay) | V37: =YEAR(U37) | W37: =EDATE(I37,-H37) | X37: =T37*ITCRate*O37 | Y37: =T37*(1-ITCBasisRed*ITCRate*O37) | Z37: =EDATE(U37,12*Q37)
B38: Delta | C38: BESS | D38: 125 | E38: 4 | F38: 325 | G38: $/kWh | H38: 14 | I38: 46935 | J38: 0.9 | K38: 0.02 | L38: 27 | M38: 45 | N38: 180 | O38: 1 | P38: 5 | Q38: 20 | R38: =F38*IF(G38="$/kWh",E38,1) | S38: =D38*E38 | T38: =D38*R38*(1+Contingency)*(1+CapexAdj) | U38: =EDATE(I38,Delay) | V38: =YEAR(U38) | W38: =EDATE(I38,-H38) | X38: =T38*ITCRate*O38 | Y38: =T38*(1-ITCBasisRed*ITCRate*O38) | Z38: =EDATE(U38,12*Q38)
B39: Echo | C39: Backup gen | D39: 50 | E39: 0 | F39: 1350 | G39: $/kW | H39: 15 | I39: 46935 | J39: 0.95 | K39: 0 | L39: 22 | M39: 10 | N39: 80 | O39: 0 | P39: 15 | Q39: 20 | R39: =F39*IF(G39="$/kWh",E39,1) | S39: =D39*E39 | T39: =D39*R39*(1+Contingency)*(1+CapexAdj) | U39: =EDATE(I39,Delay) | V39: =YEAR(U39) | W39: =EDATE(I39,-H39) | X39: =T39*ITCRate*O39 | Y39: =T39*(1-ITCBasisRed*ITCRate*O39) | Z39: =EDATE(U39,12*Q39)
B40: Portfolio | D40: =SUM(D35:D39) | S40: =SUM(S35:S39) | T40: =SUM(T35:T39) | X40: =SUM(X35:X39) | Y40: =SUM(Y35:Y39)
B41: EPC unit cost is $/kWh for storage (× duration) and $/kW for generation.
B43: MACRS depreciation (half-year convention)
B44: Tax year | C44: 5-year | D44: 15-year
B45: 1 | C45: 0.2 | D45: 0.05
B46: 2 | C46: 0.32 | D46: 0.095
B47: 3 | C47: 0.192 | D47: 0.0855
B48: 4 | C48: 0.1152 | D48: 0.077
B49: 5 | C49: 0.1152 | D49: 0.0693
B50: 6 | C50: 0.0576 | D50: 0.0623
B51: 7 | C51: 0 | D51: 0.059
B52: 8 | C52: 0 | D52: 0.059
B53: 9 | C53: 0 | D53: 0.0591
B54: 10 | C54: 0 | D54: 0.059
B55: 11 | C55: 0 | D55: 0.0591
B56: 12 | C56: 0 | D56: 0.059
... B60: 16 | C60: 0 | D60: 0.0295
B61: Total | C61: =SUM(C45:C60) | D61: =SUM(D45:D60)

Sheet Scenarios
B2: Scenarios & Sensitivities
B3: Pick the live case in C5. Sensitivity flex (column G) layers on top of the scenario. Tables below are Excel Data Tables (What-If) and refresh on recalc (F9).
B5: Active scenario (1 Base, 2 Downside, 3 Upside) | C5: 1 | D5: =INDEX(C8:E8,C5) | J5: Required capacity price solver
J6: Equity IRR across capacity-price flex (Data Table on G10); price where IRR crosses the target is interpolated.
B7: Driver | F7: Active scenario | G7: Sensitivity flex | H7: Live value | J7: Price flex | K7: Equity IRR | L7: Price $/kW-mo | N7: Solver output
B8: Scenario name | C8: Base | D8: Downside | E8: Upside | J8: Live case → | K8: =IFERROR(EqIRR,-1) | N8: First row ≥ target | O8: =IFERROR(MATCH(TRUE,INDEX($K$9:$K$49>=CostEquity,0),0),0)
B9: Capex adjustment | C9: 0 | D9: 0.1 | E9: -0.05 | F9: =CHOOSE(ScenarioSel,C9,D9,E9) | G9: 0 | H9: =F9+G9 | J9: -0.4 | L9: =CapPrice*(1+$F$10+J9) | N9: Required price flex | O9: =IF(OR(O8<=1),NA(),INDEX($J$9:$J$49,O8-1)+(CostEquity-INDEX($K$9:$K$49,O8-1))*(INDEX($J$9:$J$49,O8)-INDEX($J$9:$J$49,O8-1))/(INDEX($K$9:$K$49,O8)-INDEX($K$9:$K$49,O8-1)))
B10: Capacity price adjustment | C10: 0 | D10: -0.1 | E10: 0.05 | F10: =CHOOSE(ScenarioSel,C10,D10,E10) | G10: 0 | H10: =F10+G10 | J10: -0.38 | L10: =CapPrice*(1+$F$10+J10) | N10: Required capacity price | O10: =IFERROR(CapPrice*(1+$F$10+O9),"outside ±40%")
B11: COD delay (months) | C11: 0 | D11: 6 | E11: 0 | F11: =CHOOSE(ScenarioSel,C11,D11,E11) | G11: 0 | H11: =F11+G11 | J11: -0.36 | L11: =CapPrice*(1+$F$10+J11)
B12: Interest rate adjustment (bps) | C12: 0 | D12: 100 | E12: -50 | F12: =CHOOSE(ScenarioSel,C12,D12,E12) | G12: 0 | H12: =F12+G12 | J12: -0.34 | L12: =CapPrice*(1+$F$10+J12)
B13: Fixed O&M adjustment | C13: 0 | D13: 0.1 | E13: -0.05 | F13: =CHOOSE(ScenarioSel,C13,D13,E13) | G13: 0 | H13: =F13+G13 | J13: -0.32 | L13: =CapPrice*(1+$F$10+J13)
B14: Delay pushes every COD (and term conversion) back; construction spend timing is unchanged. | J14: -0.3 | L14: =CapPrice*(1+$F$10+J14)
J15: -0.28 | L15: =CapPrice*(1+$F$10+J15)
B16: Scenario comparison (varies C5: 1 Base · 2 Downside · 3 Upside) | J16: -0.26 | L16: =CapPrice*(1+$F$10+J16)
B17: Input ↓ / output → | C17: Equity IRR | D17: Project IRR | E17: Project NPV | F17: Equity NPV | G17: Min senior DSCR | H17: Total debt | J17: -0.24 | L17: =CapPrice*(1+$F$10+J17)
B18: Live case → | C18: =EqIRR | D18: =ProjIRR | E18: =ProjNPV | F18: =EqNPV | G18: =MinDSCRSr | H18: =SrAmt+MzAmt | J18: -0.22 | L18: =CapPrice*(1+$F$10+J18)
B19: 1 | J19: -0.2 | L19: =CapPrice*(1+$F$10+J19)
B20: 2 | J20: -0.18 | L20: =CapPrice*(1+$F$10+J20)
B21: 3 | J21: -0.16 | L21: =CapPrice*(1+$F$10+J21)
J22: -0.14 | L22: =CapPrice*(1+$F$10+J22)
B23: Capex sensitivity (flex on G9) | J23: -0.12 | L23: =CapPrice*(1+$F$10+J23)
B24: Input ↓ / output → | C24: Equity IRR | D24: Project IRR | E24: Project NPV | F24: Equity NPV | G24: Min senior DSCR | H24: Total debt | J24: -0.1 | L24: =CapPrice*(1+$F$10+J24)
B25: Live case → | C25: =EqIRR | D25: =ProjIRR | E25: =ProjNPV | F25: =EqNPV | G25: =MinDSCRSr | H25: =SrAmt+MzAmt | J25: -0.08 | L25: =CapPrice*(1+$F$10+J25)
B26: -0.2 | J26: -0.06 | L26: =CapPrice*(1+$F$10+J26)
B27: -0.1 | J27: -0.04 | L27: =CapPrice*(1+$F$10+J27)
B28: -0.05 | J28: -0.02 | L28: =CapPrice*(1+$F$10+J28)
B29: 0 | J29: 0 | L29: =CapPrice*(1+$F$10+J29)
B30: 0.05 | J30: 0.02 | L30: =CapPrice*(1+$F$10+J30)
B31: 0.1 | J31: 0.04 | L31: =CapPrice*(1+$F$10+J31)
B32: 0.2 | J32: 0.06 | L32: =CapPrice*(1+$F$10+J32)
J33: 0.08 | L33: =CapPrice*(1+$F$10+J33)
B34: Capacity price sensitivity (flex on G10) | J34: 0.1 | L34: =CapPrice*(1+$F$10+J34)
B35: Input ↓ / output → | C35: Equity IRR | D35: Project IRR | E35: Project NPV | F35: Equity NPV | G35: Min senior DSCR | H35: Total debt | J35: 0.12 | L35: =CapPrice*(1+$F$10+J35)
B36: Live case → | C36: =EqIRR | D36: =ProjIRR | E36: =ProjNPV | F36: =EqNPV | G36: =MinDSCRSr | H36: =SrAmt+MzAmt | J36: 0.14 | L36: =CapPrice*(1+$F$10+J36)
B37: -0.2 | J37: 0.16 | L37: =CapPrice*(1+$F$10+J37)
B38: -0.1 | J38: 0.18 | L38: =CapPrice*(1+$F$10+J38)
B39: -0.05 | J39: 0.2 | L39: =CapPrice*(1+$F$10+J39)
B40: 0 | J40: 0.22 | L40: =CapPrice*(1+$F$10+J40)
B41: 0.05 | J41: 0.24 | L41: =CapPrice*(1+$F$10+J41)
B42: 0.1 | J42: 0.26 | L42: =CapPrice*(1+$F$10+J42)
B43: 0.2 | J43: 0.28 | L43: =CapPrice*(1+$F$10+J43)
J44: 0.3 | L44: =CapPrice*(1+$F$10+J44)
B45: Construction delay (flex on G11, months) | J45: 0.32 | L45: =CapPrice*(1+$F$10+J45)
B46: Input ↓ / output → | C46: Equity IRR | D46: Project IRR | E46: Project NPV | F46: Equity NPV | G46: Min senior DSCR | H46: Total debt | J46: 0.34 | L46: =CapPrice*(1+$F$10+J46)
B47: Live case → | C47: =EqIRR | D47: =ProjIRR | E47: =ProjNPV | F47: =EqNPV | G47: =MinDSCRSr | H47: =SrAmt+MzAmt | J47: 0.36 | L47: =CapPrice*(1+$F$10+J47)
B48: 0 | J48: 0.38 | L48: =CapPrice*(1+$F$10+J48)
B49: 3 | J49: 0.4 | L49: =CapPrice*(1+$F$10+J49)
B50: 6
B51: 9
B52: 12
B54: Interest rates (flex on G12, bps)
B55: Input ↓ / output → | C55: Equity IRR | D55: Project IRR | E55: Project NPV | F55: Equity NPV | G55: Min senior DSCR | H55: Total debt
B56: Live case → | C56: =EqIRR | D56: =ProjIRR | E56: =ProjNPV | F56: =EqNPV | G56: =MinDSCRSr | H56: =SrAmt+MzAmt
B57: -100
B58: -50
B59: 0
B60: 50
B61: 100
B62: 200
B64: Equity IRR: capex flex (rows) × capacity price flex (columns)
B65: =EqIRR | C65: -0.2 | D65: -0.1 | E65: 0 | F65: 0.1 | G65: 0.2 | H65: Green = meets target equity IRR
B66: -0.2
B67: -0.1
B68: 0
B69: 0.1
B70: 0.2

Sheet Monthly
B2: Monthly operating cash flows
B3: Asset-level operations and capex by month, $k. Timeline columns are formulas off Inputs!ModelStart.
B5: Month starting | D5: Total | E5: =ModelStart | F5: =EDATE(E5,1) | G5: =EDATE(F5,1) | H5: =EDATE(G5,1) | I5: =EDATE(H5,1) | J5: =EDATE(I5,1) | K5: =EDATE(J5,1) | L5: =EDATE(K5,1) | M5: =EDATE(L5,1) | ... JT5: =EDATE(JS5,1)
B6: Year | E6: =YEAR(E5) | F6: =YEAR(F5) | G6: =YEAR(G5) | H6: =YEAR(H5) | I6: =YEAR(I5) | J6: =YEAR(J5) | K6: =YEAR(K5) | L6: =YEAR(L5) | ... JT6: =YEAR(JT5)
B7: Years from model start | E7: =E6-YEAR(ModelStart) | F7: =F6-YEAR(ModelStart) | G7: =G6-YEAR(ModelStart) | H7: =H6-YEAR(ModelStart) | I7: =I6-YEAR(ModelStart) | J7: =J6-YEAR(ModelStart) | K7: =K6-YEAR(ModelStart) | L7: =L6-YEAR(ModelStart) | ... JT7: =JT6-YEAR(ModelStart)
B8: Capacity price (live) | C8: $/kW-mo | E8: =CapPrice*(1+PriceAdj)*(1+PriceEsc)^E7 | F8: =CapPrice*(1+PriceAdj)*(1+PriceEsc)^F7 | G8: =CapPrice*(1+PriceAdj)*(1+PriceEsc)^G7 | H8: =CapPrice*(1+PriceAdj)*(1+PriceEsc)^H7 | I8: =CapPrice*(1+PriceAdj)*(1+PriceEsc)^I7 | J8: =CapPrice*(1+PriceAdj)*(1+PriceEsc)^J7 | K8: =CapPrice*(1+PriceAdj)*(1+PriceEsc)^K7 | L8: =CapPrice*(1+PriceAdj)*(1+PriceEsc)^L7 | ... JT8: =CapPrice*(1+PriceAdj)*(1+PriceEsc)^JT7
B9: Price escalation index | C9: x | E9: =(1+PriceEsc)^E7 | F9: =(1+PriceEsc)^F7 | G9: =(1+PriceEsc)^G7 | H9: =(1+PriceEsc)^H7 | I9: =(1+PriceEsc)^I7 | J9: =(1+PriceEsc)^J7 | K9: =(1+PriceEsc)^K7 | L9: =(1+PriceEsc)^L7 | ... JT9: =(1+PriceEsc)^JT7
B10: O&M escalation index | C10: x | E10: =(1+OMEsc)^E7 | F10: =(1+OMEsc)^F7 | G10: =(1+OMEsc)^G7 | H10: =(1+OMEsc)^H7 | I10: =(1+OMEsc)^I7 | J10: =(1+OMEsc)^J7 | K10: =(1+OMEsc)^K7 | L10: =(1+OMEsc)^L7 | ... JT10: =(1+OMEsc)^JT7
B12: Alpha — BESS 100 MW / 400 MWh
B13: Operating flag | C13: 1/0 | E13: =IF(AND(E$5>=Inputs!$U$35,E$5<Inputs!$Z$35),1,0) | F13: =IF(AND(F$5>=Inputs!$U$35,F$5<Inputs!$Z$35),1,0) | G13: =IF(AND(G$5>=Inputs!$U$35,G$5<Inputs!$Z$35),1,0) | H13: =IF(AND(H$5>=Inputs!$U$35,H$5<Inputs!$Z$35),1,0) | I13: =IF(AND(I$5>=Inputs!$U$35,I$5<Inputs!$Z$35),1,0) | J13: =IF(AND(J$5>=Inputs!$U$35,J$5<Inputs!$Z$35),1,0) | K13: =IF(AND(K$5>=Inputs!$U$35,K$5<Inputs!$Z$35),1,0) | L13: =IF(AND(L$5>=Inputs!$U$35,L$5<Inputs!$Z$35),1,0) | ... JT13: =IF(AND(JT$5>=Inputs!$U$35,JT$5<Inputs!$Z$35),1,0)
B14: Operating year | C14: # | E14: =IF(E13=1,INT(((YEAR(E$5)-YEAR(Inputs!$U$35))*12+MONTH(E$5)-MONTH(Inputs!$U$35))/12),0) | F14: =IF(F13=1,INT(((YEAR(F$5)-YEAR(Inputs!$U$35))*12+MONTH(F$5)-MONTH(Inputs!$U$35))/12),0) | G14: =IF(G13=1,INT(((YEAR(G$5)-YEAR(Inputs!$U$35))*12+MONTH(G$5)-MONTH(Inputs!$U$35))/12),0) | H14: =IF(H13=1,INT(((YEAR(H$5)-YEAR(Inputs!$U$35))*12+MONTH(H$5)-MONTH(Inputs!$U$35))/12),0) | I14: =IF(I13=1,INT(((YEAR(I$5)-YEAR(Inputs!$U$35))*12+MONTH(I$5)-MONTH(Inputs!$U$35))/12),0) | J14: =IF(J13=1,INT(((YEAR(J$5)-YEAR(Inputs!$U$35))*12+MONTH(J$5)-MONTH(Inputs!$U$35))/12),0) | K14: =IF(K13=1,INT(((YEAR(K$5)-YEAR(Inputs!$U$35))*12+MONTH(K$5)-MONTH(Inputs!$U$35))/12),0) | L14: =IF(L13=1,INT(((YEAR(L$5)-YEAR(Inputs!$U$35))*12+MONTH(L$5)-MONTH(Inputs!$U$35))/12),0) | ... JT14: =IF(JT13=1,INT(((YEAR(JT$5)-YEAR(Inputs!$U$35))*12+MONTH(JT$5)-MONTH(Inputs!$U$35))/12),0)
B15: Accredited capacity (after degradation) | C15: MW | E15: =E13*Inputs!$D$35*Inputs!$J$35*(1-Inputs!$K$35)^E14 | F15: =F13*Inputs!$D$35*Inputs!$J$35*(1-Inputs!$K$35)^F14 | G15: =G13*Inputs!$D$35*Inputs!$J$35*(1-Inputs!$K$35)^G14 | H15: =H13*Inputs!$D$35*Inputs!$J$35*(1-Inputs!$K$35)^H14 | I15: =I13*Inputs!$D$35*Inputs!$J$35*(1-Inputs!$K$35)^I14 | J15: =J13*Inputs!$D$35*Inputs!$J$35*(1-Inputs!$K$35)^J14 | K15: =K13*Inputs!$D$35*Inputs!$J$35*(1-Inputs!$K$35)^K14 | L15: =L13*Inputs!$D$35*Inputs!$J$35*(1-Inputs!$K$35)^L14 | ... JT15: =JT13*Inputs!$D$35*Inputs!$J$35*(1-Inputs!$K$35)^JT14
B16: Capacity revenue | C16: $k | D16: =SUM(E16:JT16) | E16: =E15*E$8 | F16: =F15*F$8 | G16: =G15*G$8 | H16: =H15*H$8 | I16: =I15*I$8 | J16: =J15*J$8 | K16: =K15*K$8 | L16: =L15*L$8 | ... JT16: =JT15*JT$8
B17: Energy & ancillary margin | C17: $k | D17: =SUM(E17:JT17) | E17: =E15*Inputs!$M$35/12*E$9 | F17: =F15*Inputs!$M$35/12*F$9 | G17: =G15*Inputs!$M$35/12*G$9 | H17: =H15*Inputs!$M$35/12*H$9 | I17: =I15*Inputs!$M$35/12*I$9 | J17: =J15*Inputs!$M$35/12*J$9 | K17: =K15*Inputs!$M$35/12*K$9 | L17: =L15*Inputs!$M$35/12*L$9 | ... JT17: =JT15*Inputs!$M$35/12*JT$9
B18: Fixed O&M | C18: $k | D18: =SUM(E18:JT18) | E18: =E13*Inputs!$D$35*Inputs!$L$35/12*E$10*(1+OMAdj) | F18: =F13*Inputs!$D$35*Inputs!$L$35/12*F$10*(1+OMAdj) | G18: =G13*Inputs!$D$35*Inputs!$L$35/12*G$10*(1+OMAdj) | H18: =H13*Inputs!$D$35*Inputs!$L$35/12*H$10*(1+OMAdj) | I18: =I13*Inputs!$D$35*Inputs!$L$35/12*I$10*(1+OMAdj) | J18: =J13*Inputs!$D$35*Inputs!$L$35/12*J$10*(1+OMAdj) | K18: =K13*Inputs!$D$35*Inputs!$L$35/12*K$10*(1+OMAdj) | L18: =L13*Inputs!$D$35*Inputs!$L$35/12*L$10*(1+OMAdj) | ... JT18: =JT13*Inputs!$D$35*Inputs!$L$35/12*JT$10*(1+OMAdj)
B19: Insurance & property tax | C19: $k | D19: =SUM(E19:JT19) | E19: =E13*Inputs!$T$35*(Insurance+PropTax)/12 | F19: =F13*Inputs!$T$35*(Insurance+PropTax)/12 | G19: =G13*Inputs!$T$35*(Insurance+PropTax)/12 | H19: =H13*Inputs!$T$35*(Insurance+PropTax)/12 | I19: =I13*Inputs!$T$35*(Insurance+PropTax)/12 | J19: =J13*Inputs!$T$35*(Insurance+PropTax)/12 | K19: =K13*Inputs!$T$35*(Insurance+PropTax)/12 | L19: =L13*Inputs!$T$35*(Insurance+PropTax)/12 | ... JT19: =JT13*Inputs!$T$35*(Insurance+PropTax)/12
B20: Site lease | C20: $k | D20: =SUM(E20:JT20) | E20: =E13*Inputs!$N$35/12*E$10 | F20: =F13*Inputs!$N$35/12*F$10 | G20: =G13*Inputs!$N$35/12*G$10 | H20: =H13*Inputs!$N$35/12*H$10 | I20: =I13*Inputs!$N$35/12*I$10 | J20: =J13*Inputs!$N$35/12*J$10 | K20: =K13*Inputs!$N$35/12*K$10 | L20: =L13*Inputs!$N$35/12*L$10 | ... JT20: =JT13*Inputs!$N$35/12*JT$10
B21: Construction capex | C21: $k | D21: =SUM(E21:JT21) | E21: =IF(AND(E$5>=Inputs!$W$35,E$5<Inputs!$I$35),Inputs!$T$35/Inputs!$H$35,0) | F21: =IF(AND(F$5>=Inputs!$W$35,F$5<Inputs!$I$35),Inputs!$T$35/Inputs!$H$35,0) | G21: =IF(AND(G$5>=Inputs!$W$35,G$5<Inputs!$I$35),Inputs!$T$35/Inputs!$H$35,0) | H21: =IF(AND(H$5>=Inputs!$W$35,H$5<Inputs!$I$35),Inputs!$T$35/Inputs!$H$35,0) | I21: =IF(AND(I$5>=Inputs!$W$35,I$5<Inputs!$I$35),Inputs!$T$35/Inputs!$H$35,0) | J21: =IF(AND(J$5>=Inputs!$W$35,J$5<Inputs!$I$35),Inputs!$T$35/Inputs!$H$35,0) | K21: =IF(AND(K$5>=Inputs!$W$35,K$5<Inputs!$I$35),Inputs!$T$35/Inputs!$H$35,0) | L21: =IF(AND(L$5>=Inputs!$W$35,L$5<Inputs!$I$35),Inputs!$T$35/Inputs!$H$35,0) | ... JT21: =IF(AND(JT$5>=Inputs!$W$35,JT$5<Inputs!$I$35),Inputs!$T$35/Inputs!$H$35,0)
B23: Bravo — BESS 75 MW / 300 MWh
B24: Operating flag | C24: 1/0 | E24: =IF(AND(E$5>=Inputs!$U$36,E$5<Inputs!$Z$36),1,0) | F24: =IF(AND(F$5>=Inputs!$U$36,F$5<Inputs!$Z$36),1,0) | G24: =IF(AND(G$5>=Inputs!$U$36,G$5<Inputs!$Z$36),1,0) | H24: =IF(AND(H$5>=Inputs!$U$36,H$5<Inputs!$Z$36),1,0) | I24: =IF(AND(I$5>=Inputs!$U$36,I$5<Inputs!$Z$36),1,0) | J24: =IF(AND(J$5>=Inputs!$U$36,J$5<Inputs!$Z$36),1,0) | K24: =IF(AND(K$5>=Inputs!$U$36,K$5<Inputs!$Z$36),1,0) | L24: =IF(AND(L$5>=Inputs!$U$36,L$5<Inputs!$Z$36),1,0) | ... JT24: =IF(AND(JT$5>=Inputs!$U$36,JT$5<Inputs!$Z$36),1,0)
B25: Operating year | C25: # | E25: =IF(E24=1,INT(((YEAR(E$5)-YEAR(Inputs!$U$36))*12+MONTH(E$5)-MONTH(Inputs!$U$36))/12),0) | F25: =IF(F24=1,INT(((YEAR(F$5)-YEAR(Inputs!$U$36))*12+MONTH(F$5)-MONTH(Inputs!$U$36))/12),0) | G25: =IF(G24=1,INT(((YEAR(G$5)-YEAR(Inputs!$U$36))*12+MONTH(G$5)-MONTH(Inputs!$U$36))/12),0) | H25: =IF(H24=1,INT(((YEAR(H$5)-YEAR(Inputs!$U$36))*12+MONTH(H$5)-MONTH(Inputs!$U$36))/12),0) | I25: =IF(I24=1,INT(((YEAR(I$5)-YEAR(Inputs!$U$36))*12+MONTH(I$5)-MONTH(Inputs!$U$36))/12),0) | J25: =IF(J24=1,INT(((YEAR(J$5)-YEAR(Inputs!$U$36))*12+MONTH(J$5)-MONTH(Inputs!$U$36))/12),0) | K25: =IF(K24=1,INT(((YEAR(K$5)-YEAR(Inputs!$U$36))*12+MONTH(K$5)-MONTH(Inputs!$U$36))/12),0) | L25: =IF(L24=1,INT(((YEAR(L$5)-YEAR(Inputs!$U$36))*12+MONTH(L$5)-MONTH(Inputs!$U$36))/12),0) | ... JT25: =IF(JT24=1,INT(((YEAR(JT$5)-YEAR(Inputs!$U$36))*12+MONTH(JT$5)-MONTH(Inputs!$U$36))/12),0)
B26: Accredited capacity (after degradation) | C26: MW | E26: =E24*Inputs!$D$36*Inputs!$J$36*(1-Inputs!$K$36)^E25 | F26: =F24*Inputs!$D$36*Inputs!$J$36*(1-Inputs!$K$36)^F25 | G26: =G24*Inputs!$D$36*Inputs!$J$36*(1-Inputs!$K$36)^G25 | H26: =H24*Inputs!$D$36*Inputs!$J$36*(1-Inputs!$K$36)^H25 | I26: =I24*Inputs!$D$36*Inputs!$J$36*(1-Inputs!$K$36)^I25 | J26: =J24*Inputs!$D$36*Inputs!$J$36*(1-Inputs!$K$36)^J25 | K26: =K24*Inputs!$D$36*Inputs!$J$36*(1-Inputs!$K$36)^K25 | L26: =L24*Inputs!$D$36*Inputs!$J$36*(1-Inputs!$K$36)^L25 | ... JT26: =JT24*Inputs!$D$36*Inputs!$J$36*(1-Inputs!$K$36)^JT25
B27: Capacity revenue | C27: $k | D27: =SUM(E27:JT27) | E27: =E26*E$8 | F27: =F26*F$8 | G27: =G26*G$8 | H27: =H26*H$8 | I27: =I26*I$8 | J27: =J26*J$8 | K27: =K26*K$8 | L27: =L26*L$8 | ... JT27: =JT26*JT$8
B28: Energy & ancillary margin | C28: $k | D28: =SUM(E28:JT28) | E28: =E26*Inputs!$M$36/12*E$9 | F28: =F26*Inputs!$M$36/12*F$9 | G28: =G26*Inputs!$M$36/12*G$9 | H28: =H26*Inputs!$M$36/12*H$9 | I28: =I26*Inputs!$M$36/12*I$9 | J28: =J26*Inputs!$M$36/12*J$9 | K28: =K26*Inputs!$M$36/12*K$9 | L28: =L26*Inputs!$M$36/12*L$9 | ... JT28: =JT26*Inputs!$M$36/12*JT$9
B29: Fixed O&M | C29: $k | D29: =SUM(E29:JT29) | E29: =E24*Inputs!$D$36*Inputs!$L$36/12*E$10*(1+OMAdj) | F29: =F24*Inputs!$D$36*Inputs!$L$36/12*F$10*(1+OMAdj) | G29: =G24*Inputs!$D$36*Inputs!$L$36/12*G$10*(1+OMAdj) | H29: =H24*Inputs!$D$36*Inputs!$L$36/12*H$10*(1+OMAdj) | I29: =I24*Inputs!$D$36*Inputs!$L$36/12*I$10*(1+OMAdj) | J29: =J24*Inputs!$D$36*Inputs!$L$36/12*J$10*(1+OMAdj) | K29: =K24*Inputs!$D$36*Inputs!$L$36/12*K$10*(1+OMAdj) | L29: =L24*Inputs!$D$36*Inputs!$L$36/12*L$10*(1+OMAdj) | ... JT29: =JT24*Inputs!$D$36*Inputs!$L$36/12*JT$10*(1+OMAdj)
B30: Insurance & property tax | C30: $k | D30: =SUM(E30:JT30) | E30: =E24*Inputs!$T$36*(Insurance+PropTax)/12 | F30: =F24*Inputs!$T$36*(Insurance+PropTax)/12 | G30: =G24*Inputs!$T$36*(Insurance+PropTax)/12 | H30: =H24*Inputs!$T$36*(Insurance+PropTax)/12 | I30: =I24*Inputs!$T$36*(Insurance+PropTax)/12 | J30: =J24*Inputs!$T$36*(Insurance+PropTax)/12 | K30: =K24*Inputs!$T$36*(Insurance+PropTax)/12 | L30: =L24*Inputs!$T$36*(Insurance+PropTax)/12 | ... JT30: =JT24*Inputs!$T$36*(Insurance+PropTax)/12
B31: Site lease | C31: $k | D31: =SUM(E31:JT31) | E31: =E24*Inputs!$N$36/12*E$10 | F31: =F24*Inputs!$N$36/12*F$10 | G31: =G24*Inputs!$N$36/12*G$10 | H31: =H24*Inputs!$N$36/12*H$10 | I31: =I24*Inputs!$N$36/12*I$10 | J31: =J24*Inputs!$N$36/12*J$10 | K31: =K24*Inputs!$N$36/12*K$10 | L31: =L24*Inputs!$N$36/12*L$10 | ... JT31: =JT24*Inputs!$N$36/12*JT$10
B32: Construction capex | C32: $k | D32: =SUM(E32:JT32) | E32: =IF(AND(E$5>=Inputs!$W$36,E$5<Inputs!$I$36),Inputs!$T$36/Inputs!$H$36,0) | F32: =IF(AND(F$5>=Inputs!$W$36,F$5<Inputs!$I$36),Inputs!$T$36/Inputs!$H$36,0) | G32: =IF(AND(G$5>=Inputs!$W$36,G$5<Inputs!$I$36),Inputs!$T$36/Inputs!$H$36,0) | H32: =IF(AND(H$5>=Inputs!$W$36,H$5<Inputs!$I$36),Inputs!$T$36/Inputs!$H$36,0) | I32: =IF(AND(I$5>=Inputs!$W$36,I$5<Inputs!$I$36),Inputs!$T$36/Inputs!$H$36,0) | J32: =IF(AND(J$5>=Inputs!$W$36,J$5<Inputs!$I$36),Inputs!$T$36/Inputs!$H$36,0) | K32: =IF(AND(K$5>=Inputs!$W$36,K$5<Inputs!$I$36),Inputs!$T$36/Inputs!$H$36,0) | L32: =IF(AND(L$5>=Inputs!$W$36,L$5<Inputs!$I$36),Inputs!$T$36/Inputs!$H$36,0) | ... JT32: =IF(AND(JT$5>=Inputs!$W$36,JT$5<Inputs!$I$36),Inputs!$T$36/Inputs!$H$36,0)
B34: Charlie — BESS 50 MW / 100 MWh
B35: Operating flag | C35: 1/0 | E35: =IF(AND(E$5>=Inputs!$U$37,E$5<Inputs!$Z$37),1,0) | F35: =IF(AND(F$5>=Inputs!$U$37,F$5<Inputs!$Z$37),1,0) | G35: =IF(AND(G$5>=Inputs!$U$37,G$5<Inputs!$Z$37),1,0) | H35: =IF(AND(H$5>=Inputs!$U$37,H$5<Inputs!$Z$37),1,0) | I35: =IF(AND(I$5>=Inputs!$U$37,I$5<Inputs!$Z$37),1,0) | J35: =IF(AND(J$5>=Inputs!$U$37,J$5<Inputs!$Z$37),1,0) | K35: =IF(AND(K$5>=Inputs!$U$37,K$5<Inputs!$Z$37),1,0) | L35: =IF(AND(L$5>=Inputs!$U$37,L$5<Inputs!$Z$37),1,0) | ... JT35: =IF(AND(JT$5>=Inputs!$U$37,JT$5<Inputs!$Z$37),1,0)
B36: Operating year | C36: # | E36: =IF(E35=1,INT(((YEAR(E$5)-YEAR(Inputs!$U$37))*12+MONTH(E$5)-MONTH(Inputs!$U$37))/12),0) | F36: =IF(F35=1,INT(((YEAR(F$5)-YEAR(Inputs!$U$37))*12+MONTH(F$5)-MONTH(Inputs!$U$37))/12),0) | G36: =IF(G35=1,INT(((YEAR(G$5)-YEAR(Inputs!$U$37))*12+MONTH(G$5)-MONTH(Inputs!$U$37))/12),0) | H36: =IF(H35=1,INT(((YEAR(H$5)-YEAR(Inputs!$U$37))*12+MONTH(H$5)-MONTH(Inputs!$U$37))/12),0) | I36: =IF(I35=1,INT(((YEAR(I$5)-YEAR(Inputs!$U$37))*12+MONTH(I$5)-MONTH(Inputs!$U$37))/12),0) | J36: =IF(J35=1,INT(((YEAR(J$5)-YEAR(Inputs!$U$37))*12+MONTH(J$5)-MONTH(Inputs!$U$37))/12),0) | K36: =IF(K35=1,INT(((YEAR(K$5)-YEAR(Inputs!$U$37))*12+MONTH(K$5)-MONTH(Inputs!$U$37))/12),0) | L36: =IF(L35=1,INT(((YEAR(L$5)-YEAR(Inputs!$U$37))*12+MONTH(L$5)-MONTH(Inputs!$U$37))/12),0) | ... JT36: =IF(JT35=1,INT(((YEAR(JT$5)-YEAR(Inputs!$U$37))*12+MONTH(JT$5)-MONTH(Inputs!$U$37))/12),0)
B37: Accredited capacity (after degradation) | C37: MW | E37: =E35*Inputs!$D$37*Inputs!$J$37*(1-Inputs!$K$37)^E36 | F37: =F35*Inputs!$D$37*Inputs!$J$37*(1-Inputs!$K$37)^F36 | G37: =G35*Inputs!$D$37*Inputs!$J$37*(1-Inputs!$K$37)^G36 | H37: =H35*Inputs!$D$37*Inputs!$J$37*(1-Inputs!$K$37)^H36 | I37: =I35*Inputs!$D$37*Inputs!$J$37*(1-Inputs!$K$37)^I36 | J37: =J35*Inputs!$D$37*Inputs!$J$37*(1-Inputs!$K$37)^J36 | K37: =K35*Inputs!$D$37*Inputs!$J$37*(1-Inputs!$K$37)^K36 | L37: =L35*Inputs!$D$37*Inputs!$J$37*(1-Inputs!$K$37)^L36 | ... JT37: =JT35*Inputs!$D$37*Inputs!$J$37*(1-Inputs!$K$37)^JT36
B38: Capacity revenue | C38: $k | D38: =SUM(E38:JT38) | E38: =E37*E$8 | F38: =F37*F$8 | G38: =G37*G$8 | H38: =H37*H$8 | I38: =I37*I$8 | J38: =J37*J$8 | K38: =K37*K$8 | L38: =L37*L$8 | ... JT38: =JT37*JT$8
B39: Energy & ancillary margin | C39: $k | D39: =SUM(E39:JT39) | E39: =E37*Inputs!$M$37/12*E$9 | F39: =F37*Inputs!$M$37/12*F$9 | G39: =G37*Inputs!$M$37/12*G$9 | H39: =H37*Inputs!$M$37/12*H$9 | I39: =I37*Inputs!$M$37/12*I$9 | J39: =J37*Inputs!$M$37/12*J$9 | K39: =K37*Inputs!$M$37/12*K$9 | L39: =L37*Inputs!$M$37/12*L$9 | ... JT39: =JT37*Inputs!$M$37/12*JT$9
B40: Fixed O&M | C40: $k | D40: =SUM(E40:JT40) | E40: =E35*Inputs!$D$37*Inputs!$L$37/12*E$10*(1+OMAdj) | F40: =F35*Inputs!$D$37*Inputs!$L$37/12*F$10*(1+OMAdj) | G40: =G35*Inputs!$D$37*Inputs!$L$37/12*G$10*(1+OMAdj) | H40: =H35*Inputs!$D$37*Inputs!$L$37/12*H$10*(1+OMAdj) | I40: =I35*Inputs!$D$37*Inputs!$L$37/12*I$10*(1+OMAdj) | J40: =J35*Inputs!$D$37*Inputs!$L$37/12*J$10*(1+OMAdj) | K40: =K35*Inputs!$D$37*Inputs!$L$37/12*K$10*(1+OMAdj) | L40: =L35*Inputs!$D$37*Inputs!$L$37/12*L$10*(1+OMAdj) | ... JT40: =JT35*Inputs!$D$37*Inputs!$L$37/12*JT$10*(1+OMAdj)
B41: Insurance & property tax | C41: $k | D41: =SUM(E41:JT41) | E41: =E35*Inputs!$T$37*(Insurance+PropTax)/12 | F41: =F35*Inputs!$T$37*(Insurance+PropTax)/12 | G41: =G35*Inputs!$T$37*(Insurance+PropTax)/12 | H41: =H35*Inputs!$T$37*(Insurance+PropTax)/12 | I41: =I35*Inputs!$T$37*(Insurance+PropTax)/12 | J41: =J35*Inputs!$T$37*(Insurance+PropTax)/12 | K41: =K35*Inputs!$T$37*(Insurance+PropTax)/12 | L41: =L35*Inputs!$T$37*(Insurance+PropTax)/12 | ... JT41: =JT35*Inputs!$T$37*(Insurance+PropTax)/12
B42: Site lease | C42: $k | D42: =SUM(E42:JT42) | E42: =E35*Inputs!$N$37/12*E$10 | F42: =F35*Inputs!$N$37/12*F$10 | G42: =G35*Inputs!$N$37/12*G$10 | H42: =H35*Inputs!$N$37/12*H$10 | I42: =I35*Inputs!$N$37/12*I$10 | J42: =J35*Inputs!$N$37/12*J$10 | K42: =K35*Inputs!$N$37/12*K$10 | L42: =L35*Inputs!$N$37/12*L$10 | ... JT42: =JT35*Inputs!$N$37/12*JT$10
B43: Construction capex | C43: $k | D43: =SUM(E43:JT43) | E43: =IF(AND(E$5>=Inputs!$W$37,E$5<Inputs!$I$37),Inputs!$T$37/Inputs!$H$37,0) | F43: =IF(AND(F$5>=Inputs!$W$37,F$5<Inputs!$I$37),Inputs!$T$37/Inputs!$H$37,0) | G43: =IF(AND(G$5>=Inputs!$W$37,G$5<Inputs!$I$37),Inputs!$T$37/Inputs!$H$37,0) | H43: =IF(AND(H$5>=Inputs!$W$37,H$5<Inputs!$I$37),Inputs!$T$37/Inputs!$H$37,0) | I43: =IF(AND(I$5>=Inputs!$W$37,I$5<Inputs!$I$37),Inputs!$T$37/Inputs!$H$37,0) | J43: =IF(AND(J$5>=Inputs!$W$37,J$5<Inputs!$I$37),Inputs!$T$37/Inputs!$H$37,0) | K43: =IF(AND(K$5>=Inputs!$W$37,K$5<Inputs!$I$37),Inputs!$T$37/Inputs!$H$37,0) | L43: =IF(AND(L$5>=Inputs!$W$37,L$5<Inputs!$I$37),Inputs!$T$37/Inputs!$H$37,0) | ... JT43: =IF(AND(JT$5>=Inputs!$W$37,JT$5<Inputs!$I$37),Inputs!$T$37/Inputs!$H$37,0)
B45: Delta — BESS 125 MW / 500 MWh
B46: Operating flag | C46: 1/0 | E46: =IF(AND(E$5>=Inputs!$U$38,E$5<Inputs!$Z$38),1,0) | F46: =IF(AND(F$5>=Inputs!$U$38,F$5<Inputs!$Z$38),1,0) | G46: =IF(AND(G$5>=Inputs!$U$38,G$5<Inputs!$Z$38),1,0) | H46: =IF(AND(H$5>=Inputs!$U$38,H$5<Inputs!$Z$38),1,0) | I46: =IF(AND(I$5>=Inputs!$U$38,I$5<Inputs!$Z$38),1,0) | J46: =IF(AND(J$5>=Inputs!$U$38,J$5<Inputs!$Z$38),1,0) | K46: =IF(AND(K$5>=Inputs!$U$38,K$5<Inputs!$Z$38),1,0) | L46: =IF(AND(L$5>=Inputs!$U$38,L$5<Inputs!$Z$38),1,0) | ... JT46: =IF(AND(JT$5>=Inputs!$U$38,JT$5<Inputs!$Z$38),1,0)
B47: Operating year | C47: # | E47: =IF(E46=1,INT(((YEAR(E$5)-YEAR(Inputs!$U$38))*12+MONTH(E$5)-MONTH(Inputs!$U$38))/12),0) | F47: =IF(F46=1,INT(((YEAR(F$5)-YEAR(Inputs!$U$38))*12+MONTH(F$5)-MONTH(Inputs!$U$38))/12),0) | G47: =IF(G46=1,INT(((YEAR(G$5)-YEAR(Inputs!$U$38))*12+MONTH(G$5)-MONTH(Inputs!$U$38))/12),0) | H47: =IF(H46=1,INT(((YEAR(H$5)-YEAR(Inputs!$U$38))*12+MONTH(H$5)-MONTH(Inputs!$U$38))/12),0) | I47: =IF(I46=1,INT(((YEAR(I$5)-YEAR(Inputs!$U$38))*12+MONTH(I$5)-MONTH(Inputs!$U$38))/12),0) | J47: =IF(J46=1,INT(((YEAR(J$5)-YEAR(Inputs!$U$38))*12+MONTH(J$5)-MONTH(Inputs!$U$38))/12),0) | K47: =IF(K46=1,INT(((YEAR(K$5)-YEAR(Inputs!$U$38))*12+MONTH(K$5)-MONTH(Inputs!$U$38))/12),0) | L47: =IF(L46=1,INT(((YEAR(L$5)-YEAR(Inputs!$U$38))*12+MONTH(L$5)-MONTH(Inputs!$U$38))/12),0) | ... JT47: =IF(JT46=1,INT(((YEAR(JT$5)-YEAR(Inputs!$U$38))*12+MONTH(JT$5)-MONTH(Inputs!$U$38))/12),0)
B48: Accredited capacity (after degradation) | C48: MW | E48: =E46*Inputs!$D$38*Inputs!$J$38*(1-Inputs!$K$38)^E47 | F48: =F46*Inputs!$D$38*Inputs!$J$38*(1-Inputs!$K$38)^F47 | G48: =G46*Inputs!$D$38*Inputs!$J$38*(1-Inputs!$K$38)^G47 | H48: =H46*Inputs!$D$38*Inputs!$J$38*(1-Inputs!$K$38)^H47 | I48: =I46*Inputs!$D$38*Inputs!$J$38*(1-Inputs!$K$38)^I47 | J48: =J46*Inputs!$D$38*Inputs!$J$38*(1-Inputs!$K$38)^J47 | K48: =K46*Inputs!$D$38*Inputs!$J$38*(1-Inputs!$K$38)^K47 | L48: =L46*Inputs!$D$38*Inputs!$J$38*(1-Inputs!$K$38)^L47 | ... JT48: =JT46*Inputs!$D$38*Inputs!$J$38*(1-Inputs!$K$38)^JT47
B49: Capacity revenue | C49: $k | D49: =SUM(E49:JT49) | E49: =E48*E$8 | F49: =F48*F$8 | G49: =G48*G$8 | H49: =H48*H$8 | I49: =I48*I$8 | J49: =J48*J$8 | K49: =K48*K$8 | L49: =L48*L$8 | ... JT49: =JT48*JT$8
B50: Energy & ancillary margin | C50: $k | D50: =SUM(E50:JT50) | E50: =E48*Inputs!$M$38/12*E$9 | F50: =F48*Inputs!$M$38/12*F$9 | G50: =G48*Inputs!$M$38/12*G$9 | H50: =H48*Inputs!$M$38/12*H$9 | I50: =I48*Inputs!$M$38/12*I$9 | J50: =J48*Inputs!$M$38/12*J$9 | K50: =K48*Inputs!$M$38/12*K$9 | L50: =L48*Inputs!$M$38/12*L$9 | ... JT50: =JT48*Inputs!$M$38/12*JT$9
B51: Fixed O&M | C51: $k | D51: =SUM(E51:JT51) | E51: =E46*Inputs!$D$38*Inputs!$L$38/12*E$10*(1+OMAdj) | F51: =F46*Inputs!$D$38*Inputs!$L$38/12*F$10*(1+OMAdj) | G51: =G46*Inputs!$D$38*Inputs!$L$38/12*G$10*(1+OMAdj) | H51: =H46*Inputs!$D$38*Inputs!$L$38/12*H$10*(1+OMAdj) | I51: =I46*Inputs!$D$38*Inputs!$L$38/12*I$10*(1+OMAdj) | J51: =J46*Inputs!$D$38*Inputs!$L$38/12*J$10*(1+OMAdj) | K51: =K46*Inputs!$D$38*Inputs!$L$38/12*K$10*(1+OMAdj) | L51: =L46*Inputs!$D$38*Inputs!$L$38/12*L$10*(1+OMAdj) | ... JT51: =JT46*Inputs!$D$38*Inputs!$L$38/12*JT$10*(1+OMAdj)
B52: Insurance & property tax | C52: $k | D52: =SUM(E52:JT52) | E52: =E46*Inputs!$T$38*(Insurance+PropTax)/12 | F52: =F46*Inputs!$T$38*(Insurance+PropTax)/12 | G52: =G46*Inputs!$T$38*(Insurance+PropTax)/12 | H52: =H46*Inputs!$T$38*(Insurance+PropTax)/12 | I52: =I46*Inputs!$T$38*(Insurance+PropTax)/12 | J52: =J46*Inputs!$T$38*(Insurance+PropTax)/12 | K52: =K46*Inputs!$T$38*(Insurance+PropTax)/12 | L52: =L46*Inputs!$T$38*(Insurance+PropTax)/12 | ... JT52: =JT46*Inputs!$T$38*(Insurance+PropTax)/12
B53: Site lease | C53: $k | D53: =SUM(E53:JT53) | E53: =E46*Inputs!$N$38/12*E$10 | F53: =F46*Inputs!$N$38/12*F$10 | G53: =G46*Inputs!$N$38/12*G$10 | H53: =H46*Inputs!$N$38/12*H$10 | I53: =I46*Inputs!$N$38/12*I$10 | J53: =J46*Inputs!$N$38/12*J$10 | K53: =K46*Inputs!$N$38/12*K$10 | L53: =L46*Inputs!$N$38/12*L$10 | ... JT53: =JT46*Inputs!$N$38/12*JT$10
B54: Construction capex | C54: $k | D54: =SUM(E54:JT54) | E54: =IF(AND(E$5>=Inputs!$W$38,E$5<Inputs!$I$38),Inputs!$T$38/Inputs!$H$38,0) | F54: =IF(AND(F$5>=Inputs!$W$38,F$5<Inputs!$I$38),Inputs!$T$38/Inputs!$H$38,0) | G54: =IF(AND(G$5>=Inputs!$W$38,G$5<Inputs!$I$38),Inputs!$T$38/Inputs!$H$38,0) | H54: =IF(AND(H$5>=Inputs!$W$38,H$5<Inputs!$I$38),Inputs!$T$38/Inputs!$H$38,0) | I54: =IF(AND(I$5>=Inputs!$W$38,I$5<Inputs!$I$38),Inputs!$T$38/Inputs!$H$38,0) | J54: =IF(AND(J$5>=Inputs!$W$38,J$5<Inputs!$I$38),Inputs!$T$38/Inputs!$H$38,0) | K54: =IF(AND(K$5>=Inputs!$W$38,K$5<Inputs!$I$38),Inputs!$T$38/Inputs!$H$38,0) | L54: =IF(AND(L$5>=Inputs!$W$38,L$5<Inputs!$I$38),Inputs!$T$38/Inputs!$H$38,0) | ... JT54: =IF(AND(JT$5>=Inputs!$W$38,JT$5<Inputs!$I$38),Inputs!$T$38/Inputs!$H$38,0)
B56: Echo — Backup gen 50 MW
B57: Operating flag | C57: 1/0 | E57: =IF(AND(E$5>=Inputs!$U$39,E$5<Inputs!$Z$39),1,0) | F57: =IF(AND(F$5>=Inputs!$U$39,F$5<Inputs!$Z$39),1,0) | G57: =IF(AND(G$5>=Inputs!$U$39,G$5<Inputs!$Z$39),1,0) | H57: =IF(AND(H$5>=Inputs!$U$39,H$5<Inputs!$Z$39),1,0) | I57: =IF(AND(I$5>=Inputs!$U$39,I$5<Inputs!$Z$39),1,0) | J57: =IF(AND(J$5>=Inputs!$U$39,J$5<Inputs!$Z$39),1,0) | K57: =IF(AND(K$5>=Inputs!$U$39,K$5<Inputs!$Z$39),1,0) | L57: =IF(AND(L$5>=Inputs!$U$39,L$5<Inputs!$Z$39),1,0) | ... JT57: =IF(AND(JT$5>=Inputs!$U$39,JT$5<Inputs!$Z$39),1,0)
B58: Operating year | C58: # | E58: =IF(E57=1,INT(((YEAR(E$5)-YEAR(Inputs!$U$39))*12+MONTH(E$5)-MONTH(Inputs!$U$39))/12),0) | F58: =IF(F57=1,INT(((YEAR(F$5)-YEAR(Inputs!$U$39))*12+MONTH(F$5)-MONTH(Inputs!$U$39))/12),0) | G58: =IF(G57=1,INT(((YEAR(G$5)-YEAR(Inputs!$U$39))*12+MONTH(G$5)-MONTH(Inputs!$U$39))/12),0) | H58: =IF(H57=1,INT(((YEAR(H$5)-YEAR(Inputs!$U$39))*12+MONTH(H$5)-MONTH(Inputs!$U$39))/12),0) | I58: =IF(I57=1,INT(((YEAR(I$5)-YEAR(Inputs!$U$39))*12+MONTH(I$5)-MONTH(Inputs!$U$39))/12),0) | J58: =IF(J57=1,INT(((YEAR(J$5)-YEAR(Inputs!$U$39))*12+MONTH(J$5)-MONTH(Inputs!$U$39))/12),0) | K58: =IF(K57=1,INT(((YEAR(K$5)-YEAR(Inputs!$U$39))*12+MONTH(K$5)-MONTH(Inputs!$U$39))/12),0) | L58: =IF(L57=1,INT(((YEAR(L$5)-YEAR(Inputs!$U$39))*12+MONTH(L$5)-MONTH(Inputs!$U$39))/12),0) | ... JT58: =IF(JT57=1,INT(((YEAR(JT$5)-YEAR(Inputs!$U$39))*12+MONTH(JT$5)-MONTH(Inputs!$U$39))/12),0)
B59: Accredited capacity (after degradation) | C59: MW | E59: =E57*Inputs!$D$39*Inputs!$J$39*(1-Inputs!$K$39)^E58 | F59: =F57*Inputs!$D$39*Inputs!$J$39*(1-Inputs!$K$39)^F58 | G59: =G57*Inputs!$D$39*Inputs!$J$39*(1-Inputs!$K$39)^G58 | H59: =H57*Inputs!$D$39*Inputs!$J$39*(1-Inputs!$K$39)^H58 | I59: =I57*Inputs!$D$39*Inputs!$J$39*(1-Inputs!$K$39)^I58 | J59: =J57*Inputs!$D$39*Inputs!$J$39*(1-Inputs!$K$39)^J58 | K59: =K57*Inputs!$D$39*Inputs!$J$39*(1-Inputs!$K$39)^K58 | L59: =L57*Inputs!$D$39*Inputs!$J$39*(1-Inputs!$K$39)^L58 | ... JT59: =JT57*Inputs!$D$39*Inputs!$J$39*(1-Inputs!$K$39)^JT58
B60: Capacity revenue | C60: $k | D60: =SUM(E60:JT60) | E60: =E59*E$8 | F60: =F59*F$8 | G60: =G59*G$8 | H60: =H59*H$8 | I60: =I59*I$8 | J60: =J59*J$8 | K60: =K59*K$8 | L60: =L59*L$8 | ... JT60: =JT59*JT$8
B61: Energy & ancillary margin | C61: $k | D61: =SUM(E61:JT61) | E61: =E59*Inputs!$M$39/12*E$9 | F61: =F59*Inputs!$M$39/12*F$9 | G61: =G59*Inputs!$M$39/12*G$9 | H61: =H59*Inputs!$M$39/12*H$9 | I61: =I59*Inputs!$M$39/12*I$9 | J61: =J59*Inputs!$M$39/12*J$9 | K61: =K59*Inputs!$M$39/12*K$9 | L61: =L59*Inputs!$M$39/12*L$9 | ... JT61: =JT59*Inputs!$M$39/12*JT$9
B62: Fixed O&M | C62: $k | D62: =SUM(E62:JT62) | E62: =E57*Inputs!$D$39*Inputs!$L$39/12*E$10*(1+OMAdj) | F62: =F57*Inputs!$D$39*Inputs!$L$39/12*F$10*(1+OMAdj) | G62: =G57*Inputs!$D$39*Inputs!$L$39/12*G$10*(1+OMAdj) | H62: =H57*Inputs!$D$39*Inputs!$L$39/12*H$10*(1+OMAdj) | I62: =I57*Inputs!$D$39*Inputs!$L$39/12*I$10*(1+OMAdj) | J62: =J57*Inputs!$D$39*Inputs!$L$39/12*J$10*(1+OMAdj) | K62: =K57*Inputs!$D$39*Inputs!$L$39/12*K$10*(1+OMAdj) | L62: =L57*Inputs!$D$39*Inputs!$L$39/12*L$10*(1+OMAdj) | ... JT62: =JT57*Inputs!$D$39*Inputs!$L$39/12*JT$10*(1+OMAdj)
B63: Insurance & property tax | C63: $k | D63: =SUM(E63:JT63) | E63: =E57*Inputs!$T$39*(Insurance+PropTax)/12 | F63: =F57*Inputs!$T$39*(Insurance+PropTax)/12 | G63: =G57*Inputs!$T$39*(Insurance+PropTax)/12 | H63: =H57*Inputs!$T$39*(Insurance+PropTax)/12 | I63: =I57*Inputs!$T$39*(Insurance+PropTax)/12 | J63: =J57*Inputs!$T$39*(Insurance+PropTax)/12 | K63: =K57*Inputs!$T$39*(Insurance+PropTax)/12 | L63: =L57*Inputs!$T$39*(Insurance+PropTax)/12 | ... JT63: =JT57*Inputs!$T$39*(Insurance+PropTax)/12
B64: Site lease | C64: $k | D64: =SUM(E64:JT64) | E64: =E57*Inputs!$N$39/12*E$10 | F64: =F57*Inputs!$N$39/12*F$10 | G64: =G57*Inputs!$N$39/12*G$10 | H64: =H57*Inputs!$N$39/12*H$10 | I64: =I57*Inputs!$N$39/12*I$10 | J64: =J57*Inputs!$N$39/12*J$10 | K64: =K57*Inputs!$N$39/12*K$10 | L64: =L57*Inputs!$N$39/12*L$10 | ... JT64: =JT57*Inputs!$N$39/12*JT$10
B65: Construction capex | C65: $k | D65: =SUM(E65:JT65) | E65: =IF(AND(E$5>=Inputs!$W$39,E$5<Inputs!$I$39),Inputs!$T$39/Inputs!$H$39,0) | F65: =IF(AND(F$5>=Inputs!$W$39,F$5<Inputs!$I$39),Inputs!$T$39/Inputs!$H$39,0) | G65: =IF(AND(G$5>=Inputs!$W$39,G$5<Inputs!$I$39),Inputs!$T$39/Inputs!$H$39,0) | H65: =IF(AND(H$5>=Inputs!$W$39,H$5<Inputs!$I$39),Inputs!$T$39/Inputs!$H$39,0) | I65: =IF(AND(I$5>=Inputs!$W$39,I$5<Inputs!$I$39),Inputs!$T$39/Inputs!$H$39,0) | J65: =IF(AND(J$5>=Inputs!$W$39,J$5<Inputs!$I$39),Inputs!$T$39/Inputs!$H$39,0) | K65: =IF(AND(K$5>=Inputs!$W$39,K$5<Inputs!$I$39),Inputs!$T$39/Inputs!$H$39,0) | L65: =IF(AND(L$5>=Inputs!$W$39,L$5<Inputs!$I$39),Inputs!$T$39/Inputs!$H$39,0) | ... JT65: =IF(AND(JT$5>=Inputs!$W$39,JT$5<Inputs!$I$39),Inputs!$T$39/Inputs!$H$39,0)
B67: Portfolio total
B68: Accredited capacity | C68: MW | E68: =E15+E26+E37+E48+E59 | F68: =F15+F26+F37+F48+F59 | G68: =G15+G26+G37+G48+G59 | H68: =H15+H26+H37+H48+H59 | I68: =I15+I26+I37+I48+I59 | J68: =J15+J26+J37+J48+J59 | K68: =K15+K26+K37+K48+K59 | L68: =L15+L26+L37+L48+L59 | ... JT68: =JT15+JT26+JT37+JT48+JT59
B69: Capacity revenue | C69: $k | D69: =SUM(E69:JT69) | E69: =E16+E27+E38+E49+E60 | F69: =F16+F27+F38+F49+F60 | G69: =G16+G27+G38+G49+G60 | H69: =H16+H27+H38+H49+H60 | I69: =I16+I27+I38+I49+I60 | J69: =J16+J27+J38+J49+J60 | K69: =K16+K27+K38+K49+K60 | L69: =L16+L27+L38+L49+L60 | ... JT69: =JT16+JT27+JT38+JT49+JT60
B70: Energy & ancillary margin | C70: $k | D70: =SUM(E70:JT70) | E70: =E17+E28+E39+E50+E61 | F70: =F17+F28+F39+F50+F61 | G70: =G17+G28+G39+G50+G61 | H70: =H17+H28+H39+H50+H61 | I70: =I17+I28+I39+I50+I61 | J70: =J17+J28+J39+J50+J61 | K70: =K17+K28+K39+K50+K61 | L70: =L17+L28+L39+L50+L61 | ... JT70: =JT17+JT28+JT39+JT50+JT61
B71: Total revenue | C71: $k | D71: =SUM(E71:JT71) | E71: =E69+E70 | F71: =F69+F70 | G71: =G69+G70 | H71: =H69+H70 | I71: =I69+I70 | J71: =J69+J70 | K71: =K69+K70 | L71: =L69+L70 | ... JT71: =JT69+JT70
B72: Fixed O&M | C72: $k | D72: =SUM(E72:JT72) | E72: =E18+E29+E40+E51+E62 | F72: =F18+F29+F40+F51+F62 | G72: =G18+G29+G40+G51+G62 | H72: =H18+H29+H40+H51+H62 | I72: =I18+I29+I40+I51+I62 | J72: =J18+J29+J40+J51+J62 | K72: =K18+K29+K40+K51+K62 | L72: =L18+L29+L40+L51+L62 | ... JT72: =JT18+JT29+JT40+JT51+JT62
B73: Insurance & property tax | C73: $k | D73: =SUM(E73:JT73) | E73: =E19+E30+E41+E52+E63 | F73: =F19+F30+F41+F52+F63 | G73: =G19+G30+G41+G52+G63 | H73: =H19+H30+H41+H52+H63 | I73: =I19+I30+I41+I52+I63 | J73: =J19+J30+J41+J52+J63 | K73: =K19+K30+K41+K52+K63 | L73: =L19+L30+L41+L52+L63 | ... JT73: =JT19+JT30+JT41+JT52+JT63
B74: Site lease | C74: $k | D74: =SUM(E74:JT74) | E74: =E20+E31+E42+E53+E64 | F74: =F20+F31+F42+F53+F64 | G74: =G20+G31+G42+G53+G64 | H74: =H20+H31+H42+H53+H64 | I74: =I20+I31+I42+I53+I64 | J74: =J20+J31+J42+J53+J64 | K74: =K20+K31+K42+K53+K64 | L74: =L20+L31+L42+L53+L64 | ... JT74: =JT20+JT31+JT42+JT53+JT64
B75: Portfolio G&A | C75: $k | D75: =SUM(E75:JT75) | E75: =IF((E13+E24+E35+E46+E57)>0,1,0)*GACost/12*E$10 | F75: =IF((F13+F24+F35+F46+F57)>0,1,0)*GACost/12*F$10 | G75: =IF((G13+G24+G35+G46+G57)>0,1,0)*GACost/12*G$10 | H75: =IF((H13+H24+H35+H46+H57)>0,1,0)*GACost/12*H$10 | I75: =IF((I13+I24+I35+I46+I57)>0,1,0)*GACost/12*I$10 | J75: =IF((J13+J24+J35+J46+J57)>0,1,0)*GACost/12*J$10 | K75: =IF((K13+K24+K35+K46+K57)>0,1,0)*GACost/12*K$10 | L75: =IF((L13+L24+L35+L46+L57)>0,1,0)*GACost/12*L$10 | ... JT75: =IF((JT13+JT24+JT35+JT46+JT57)>0,1,0)*GACost/12*JT$10
B76: Total operating costs | C76: $k | D76: =SUM(E76:JT76) | E76: =SUM(E72:E75) | F76: =SUM(F72:F75) | G76: =SUM(G72:G75) | H76: =SUM(H72:H75) | I76: =SUM(I72:I75) | J76: =SUM(J72:J75) | K76: =SUM(K72:K75) | L76: =SUM(L72:L75) | ... JT76: =SUM(JT72:JT75)
B77: EBITDA | C77: $k | D77: =SUM(E77:JT77) | E77: =E71-E76 | F77: =F71-F76 | G77: =G71-G76 | H77: =H71-H76 | I77: =I71-I76 | J77: =J71-J76 | K77: =K71-K76 | L77: =L71-L76 | ... JT77: =JT71-JT76
B78: Construction capex | C78: $k | D78: =SUM(E78:JT78) | E78: =E21+E32+E43+E54+E65 | F78: =F21+F32+F43+F54+F65 | G78: =G21+G32+G43+G54+G65 | H78: =H21+H32+H43+H54+H65 | I78: =I21+I32+I43+I54+I65 | J78: =J21+J32+J43+J54+J65 | K78: =K21+K32+K43+K54+K65 | L78: =L21+L32+L43+L54+L65 | ... JT78: =JT21+JT32+JT43+JT54+JT65

Sheet Annual
B2: Annual cash flows, debt & returns
B3: Monthly operations rolled up by calendar year; debt sized and repaid annually. $k.
B5: Year | C5: Scalar | D5: Total | E5: =YEAR(ModelStart) | F5: =E5+1 | G5: =F5+1 | H5: =G5+1 | I5: =H5+1 | J5: =I5+1 | K5: =J5+1 | L5: =K5+1 | M5: =L5+1 | ... AA5: =Z5+1
B7: Operations
B8: Capacity revenue | D8: =SUM(E8:AA8) | E8: =SUMIF(Monthly!$E$6:$JT$6,E$5,Monthly!$E$69:$JT$69) | F8: =SUMIF(Monthly!$E$6:$JT$6,F$5,Monthly!$E$69:$JT$69) | G8: =SUMIF(Monthly!$E$6:$JT$6,G$5,Monthly!$E$69:$JT$69) | H8: =SUMIF(Monthly!$E$6:$JT$6,H$5,Monthly!$E$69:$JT$69) | I8: =SUMIF(Monthly!$E$6:$JT$6,I$5,Monthly!$E$69:$JT$69) | J8: =SUMIF(Monthly!$E$6:$JT$6,J$5,Monthly!$E$69:$JT$69) | K8: =SUMIF(Monthly!$E$6:$JT$6,K$5,Monthly!$E$69:$JT$69) | L8: =SUMIF(Monthly!$E$6:$JT$6,L$5,Monthly!$E$69:$JT$69) | ... AA8: =SUMIF(Monthly!$E$6:$JT$6,AA$5,Monthly!$E$69:$JT$69)
B9: Energy & ancillary margin | D9: =SUM(E9:AA9) | E9: =SUMIF(Monthly!$E$6:$JT$6,E$5,Monthly!$E$70:$JT$70) | F9: =SUMIF(Monthly!$E$6:$JT$6,F$5,Monthly!$E$70:$JT$70) | G9: =SUMIF(Monthly!$E$6:$JT$6,G$5,Monthly!$E$70:$JT$70) | H9: =SUMIF(Monthly!$E$6:$JT$6,H$5,Monthly!$E$70:$JT$70) | I9: =SUMIF(Monthly!$E$6:$JT$6,I$5,Monthly!$E$70:$JT$70) | J9: =SUMIF(Monthly!$E$6:$JT$6,J$5,Monthly!$E$70:$JT$70) | K9: =SUMIF(Monthly!$E$6:$JT$6,K$5,Monthly!$E$70:$JT$70) | L9: =SUMIF(Monthly!$E$6:$JT$6,L$5,Monthly!$E$70:$JT$70) | ... AA9: =SUMIF(Monthly!$E$6:$JT$6,AA$5,Monthly!$E$70:$JT$70)
B10: Total revenue | D10: =SUM(E10:AA10) | E10: =E8+E9 | F10: =F8+F9 | G10: =G8+G9 | H10: =H8+H9 | I10: =I8+I9 | J10: =J8+J9 | K10: =K8+K9 | L10: =L8+L9 | ... AA10: =AA8+AA9
B11: Fixed O&M | D11: =SUM(E11:AA11) | E11: =SUMIF(Monthly!$E$6:$JT$6,E$5,Monthly!$E$72:$JT$72) | F11: =SUMIF(Monthly!$E$6:$JT$6,F$5,Monthly!$E$72:$JT$72) | G11: =SUMIF(Monthly!$E$6:$JT$6,G$5,Monthly!$E$72:$JT$72) | H11: =SUMIF(Monthly!$E$6:$JT$6,H$5,Monthly!$E$72:$JT$72) | I11: =SUMIF(Monthly!$E$6:$JT$6,I$5,Monthly!$E$72:$JT$72) | J11: =SUMIF(Monthly!$E$6:$JT$6,J$5,Monthly!$E$72:$JT$72) | K11: =SUMIF(Monthly!$E$6:$JT$6,K$5,Monthly!$E$72:$JT$72) | L11: =SUMIF(Monthly!$E$6:$JT$6,L$5,Monthly!$E$72:$JT$72) | ... AA11: =SUMIF(Monthly!$E$6:$JT$6,AA$5,Monthly!$E$72:$JT$72)
B12: Insurance & property tax | D12: =SUM(E12:AA12) | E12: =SUMIF(Monthly!$E$6:$JT$6,E$5,Monthly!$E$73:$JT$73) | F12: =SUMIF(Monthly!$E$6:$JT$6,F$5,Monthly!$E$73:$JT$73) | G12: =SUMIF(Monthly!$E$6:$JT$6,G$5,Monthly!$E$73:$JT$73) | H12: =SUMIF(Monthly!$E$6:$JT$6,H$5,Monthly!$E$73:$JT$73) | I12: =SUMIF(Monthly!$E$6:$JT$6,I$5,Monthly!$E$73:$JT$73) | J12: =SUMIF(Monthly!$E$6:$JT$6,J$5,Monthly!$E$73:$JT$73) | K12: =SUMIF(Monthly!$E$6:$JT$6,K$5,Monthly!$E$73:$JT$73) | L12: =SUMIF(Monthly!$E$6:$JT$6,L$5,Monthly!$E$73:$JT$73) | ... AA12: =SUMIF(Monthly!$E$6:$JT$6,AA$5,Monthly!$E$73:$JT$73)
B13: Site lease | D13: =SUM(E13:AA13) | E13: =SUMIF(Monthly!$E$6:$JT$6,E$5,Monthly!$E$74:$JT$74) | F13: =SUMIF(Monthly!$E$6:$JT$6,F$5,Monthly!$E$74:$JT$74) | G13: =SUMIF(Monthly!$E$6:$JT$6,G$5,Monthly!$E$74:$JT$74) | H13: =SUMIF(Monthly!$E$6:$JT$6,H$5,Monthly!$E$74:$JT$74) | I13: =SUMIF(Monthly!$E$6:$JT$6,I$5,Monthly!$E$74:$JT$74) | J13: =SUMIF(Monthly!$E$6:$JT$6,J$5,Monthly!$E$74:$JT$74) | K13: =SUMIF(Monthly!$E$6:$JT$6,K$5,Monthly!$E$74:$JT$74) | L13: =SUMIF(Monthly!$E$6:$JT$6,L$5,Monthly!$E$74:$JT$74) | ... AA13: =SUMIF(Monthly!$E$6:$JT$6,AA$5,Monthly!$E$74:$JT$74)
B14: Portfolio G&A | D14: =SUM(E14:AA14) | E14: =SUMIF(Monthly!$E$6:$JT$6,E$5,Monthly!$E$75:$JT$75) | F14: =SUMIF(Monthly!$E$6:$JT$6,F$5,Monthly!$E$75:$JT$75) | G14: =SUMIF(Monthly!$E$6:$JT$6,G$5,Monthly!$E$75:$JT$75) | H14: =SUMIF(Monthly!$E$6:$JT$6,H$5,Monthly!$E$75:$JT$75) | I14: =SUMIF(Monthly!$E$6:$JT$6,I$5,Monthly!$E$75:$JT$75) | J14: =SUMIF(Monthly!$E$6:$JT$6,J$5,Monthly!$E$75:$JT$75) | K14: =SUMIF(Monthly!$E$6:$JT$6,K$5,Monthly!$E$75:$JT$75) | L14: =SUMIF(Monthly!$E$6:$JT$6,L$5,Monthly!$E$75:$JT$75) | ... AA14: =SUMIF(Monthly!$E$6:$JT$6,AA$5,Monthly!$E$75:$JT$75)
B15: Total operating costs | D15: =SUM(E15:AA15) | E15: =SUM(E11:E14) | F15: =SUM(F11:F14) | G15: =SUM(G11:G14) | H15: =SUM(H11:H14) | I15: =SUM(I11:I14) | J15: =SUM(J11:J14) | K15: =SUM(K11:K14) | L15: =SUM(L11:L14) | ... AA15: =SUM(AA11:AA14)
B16: EBITDA (= pre-tax CFADS) | D16: =SUM(E16:AA16) | E16: =E10-E15 | F16: =F10-F15 | G16: =G10-G15 | H16: =H10-H15 | I16: =I10-I15 | J16: =J10-J15 | K16: =K10-K15 | L16: =L10-L15 | ... AA16: =AA10-AA15
B17: EBITDA margin | E17: =IF(E10=0,0,E16/E10) | F17: =IF(F10=0,0,F16/F10) | G17: =IF(G10=0,0,G16/G10) | H17: =IF(H10=0,0,H16/H10) | I17: =IF(I10=0,0,I16/I10) | J17: =IF(J10=0,0,J16/J10) | K17: =IF(K10=0,0,K16/K10) | L17: =IF(L10=0,0,L16/L10) | ... AA17: =IF(AA10=0,0,AA16/AA10)
B19: Capex, ITC & tax depreciation
B20: Construction capex | C20: =D20 | D20: =SUM(E20:AA20) | E20: =SUMIF(Monthly!$E$6:$JT$6,E$5,Monthly!$E$78:$JT$78) | F20: =SUMIF(Monthly!$E$6:$JT$6,F$5,Monthly!$E$78:$JT$78) | G20: =SUMIF(Monthly!$E$6:$JT$6,G$5,Monthly!$E$78:$JT$78) | H20: =SUMIF(Monthly!$E$6:$JT$6,H$5,Monthly!$E$78:$JT$78) | I20: =SUMIF(Monthly!$E$6:$JT$6,I$5,Monthly!$E$78:$JT$78) | J20: =SUMIF(Monthly!$E$6:$JT$6,J$5,Monthly!$E$78:$JT$78) | K20: =SUMIF(Monthly!$E$6:$JT$6,K$5,Monthly!$E$78:$JT$78) | L20: =SUMIF(Monthly!$E$6:$JT$6,L$5,Monthly!$E$78:$JT$78) | ... AA20: =SUMIF(Monthly!$E$6:$JT$6,AA$5,Monthly!$E$78:$JT$78)
B21: ITC cash received (transfer) | D21: =SUM(E21:AA21) | E21: =SUMPRODUCT((Inputs!$V$35:$V$39+1=E$5)*Inputs!$X$35:$X$39)*ITCTransfer | F21: =SUMPRODUCT((Inputs!$V$35:$V$39+1=F$5)*Inputs!$X$35:$X$39)*ITCTransfer | G21: =SUMPRODUCT((Inputs!$V$35:$V$39+1=G$5)*Inputs!$X$35:$X$39)*ITCTransfer | H21: =SUMPRODUCT((Inputs!$V$35:$V$39+1=H$5)*Inputs!$X$35:$X$39)*ITCTransfer | I21: =SUMPRODUCT((Inputs!$V$35:$V$39+1=I$5)*Inputs!$X$35:$X$39)*ITCTransfer | J21: =SUMPRODUCT((Inputs!$V$35:$V$39+1=J$5)*Inputs!$X$35:$X$39)*ITCTransfer | K21: =SUMPRODUCT((Inputs!$V$35:$V$39+1=K$5)*Inputs!$X$35:$X$39)*ITCTransfer | L21: =SUMPRODUCT((Inputs!$V$35:$V$39+1=L$5)*Inputs!$X$35:$X$39)*ITCTransfer | ... AA21: =SUMPRODUCT((Inputs!$V$35:$V$39+1=AA$5)*Inputs!$X$35:$X$39)*ITCTransfer
B22: Tax depreciation — Alpha | D22: =SUM(E22:AA22) | E22: =IF(OR((E$5-Inputs!$V$35+1)<1,(E$5-Inputs!$V$35+1)>16),0,IF(Inputs!$P$35=5,INDEX(MACRS_5,(E$5-Inputs!$V$35+1)),INDEX(MACRS_15,(E$5-Inputs!$V$35+1))))*Inputs!$Y$35 | F22: =IF(OR((F$5-Inputs!$V$35+1)<1,(F$5-Inputs!$V$35+1)>16),0,IF(Inputs!$P$35=5,INDEX(MACRS_5,(F$5-Inputs!$V$35+1)),INDEX(MACRS_15,(F$5-Inputs!$V$35+1))))*Inputs!$Y$35 | G22: =IF(OR((G$5-Inputs!$V$35+1)<1,(G$5-Inputs!$V$35+1)>16),0,IF(Inputs!$P$35=5,INDEX(MACRS_5,(G$5-Inputs!$V$35+1)),INDEX(MACRS_15,(G$5-Inputs!$V$35+1))))*Inputs!$Y$35 | H22: =IF(OR((H$5-Inputs!$V$35+1)<1,(H$5-Inputs!$V$35+1)>16),0,IF(Inputs!$P$35=5,INDEX(MACRS_5,(H$5-Inputs!$V$35+1)),INDEX(MACRS_15,(H$5-Inputs!$V$35+1))))*Inputs!$Y$35 | I22: =IF(OR((I$5-Inputs!$V$35+1)<1,(I$5-Inputs!$V$35+1)>16),0,IF(Inputs!$P$35=5,INDEX(MACRS_5,(I$5-Inputs!$V$35+1)),INDEX(MACRS_15,(I$5-Inputs!$V$35+1))))*Inputs!$Y$35 | J22: =IF(OR((J$5-Inputs!$V$35+1)<1,(J$5-Inputs!$V$35+1)>16),0,IF(Inputs!$P$35=5,INDEX(MACRS_5,(J$5-Inputs!$V$35+1)),INDEX(MACRS_15,(J$5-Inputs!$V$35+1))))*Inputs!$Y$35 | K22: =IF(OR((K$5-Inputs!$V$35+1)<1,(K$5-Inputs!$V$35+1)>16),0,IF(Inputs!$P$35=5,INDEX(MACRS_5,(K$5-Inputs!$V$35+1)),INDEX(MACRS_15,(K$5-Inputs!$V$35+1))))*Inputs!$Y$35 | L22: =IF(OR((L$5-Inputs!$V$35+1)<1,(L$5-Inputs!$V$35+1)>16),0,IF(Inputs!$P$35=5,INDEX(MACRS_5,(L$5-Inputs!$V$35+1)),INDEX(MACRS_15,(L$5-Inputs!$V$35+1))))*Inputs!$Y$35 | ... AA22: =IF(OR((AA$5-Inputs!$V$35+1)<1,(AA$5-Inputs!$V$35+1)>16),0,IF(Inputs!$P$35=5,INDEX(MACRS_5,(AA$5-Inputs!$V$35+1)),INDEX(MACRS_15,(AA$5-Inputs!$V$35+1))))*Inputs!$Y$35
B23: Tax depreciation — Bravo | D23: =SUM(E23:AA23) | E23: =IF(OR((E$5-Inputs!$V$36+1)<1,(E$5-Inputs!$V$36+1)>16),0,IF(Inputs!$P$36=5,INDEX(MACRS_5,(E$5-Inputs!$V$36+1)),INDEX(MACRS_15,(E$5-Inputs!$V$36+1))))*Inputs!$Y$36 | F23: =IF(OR((F$5-Inputs!$V$36+1)<1,(F$5-Inputs!$V$36+1)>16),0,IF(Inputs!$P$36=5,INDEX(MACRS_5,(F$5-Inputs!$V$36+1)),INDEX(MACRS_15,(F$5-Inputs!$V$36+1))))*Inputs!$Y$36 | G23: =IF(OR((G$5-Inputs!$V$36+1)<1,(G$5-Inputs!$V$36+1)>16),0,IF(Inputs!$P$36=5,INDEX(MACRS_5,(G$5-Inputs!$V$36+1)),INDEX(MACRS_15,(G$5-Inputs!$V$36+1))))*Inputs!$Y$36 | H23: =IF(OR((H$5-Inputs!$V$36+1)<1,(H$5-Inputs!$V$36+1)>16),0,IF(Inputs!$P$36=5,INDEX(MACRS_5,(H$5-Inputs!$V$36+1)),INDEX(MACRS_15,(H$5-Inputs!$V$36+1))))*Inputs!$Y$36 | I23: =IF(OR((I$5-Inputs!$V$36+1)<1,(I$5-Inputs!$V$36+1)>16),0,IF(Inputs!$P$36=5,INDEX(MACRS_5,(I$5-Inputs!$V$36+1)),INDEX(MACRS_15,(I$5-Inputs!$V$36+1))))*Inputs!$Y$36 | J23: =IF(OR((J$5-Inputs!$V$36+1)<1,(J$5-Inputs!$V$36+1)>16),0,IF(Inputs!$P$36=5,INDEX(MACRS_5,(J$5-Inputs!$V$36+1)),INDEX(MACRS_15,(J$5-Inputs!$V$36+1))))*Inputs!$Y$36 | K23: =IF(OR((K$5-Inputs!$V$36+1)<1,(K$5-Inputs!$V$36+1)>16),0,IF(Inputs!$P$36=5,INDEX(MACRS_5,(K$5-Inputs!$V$36+1)),INDEX(MACRS_15,(K$5-Inputs!$V$36+1))))*Inputs!$Y$36 | L23: =IF(OR((L$5-Inputs!$V$36+1)<1,(L$5-Inputs!$V$36+1)>16),0,IF(Inputs!$P$36=5,INDEX(MACRS_5,(L$5-Inputs!$V$36+1)),INDEX(MACRS_15,(L$5-Inputs!$V$36+1))))*Inputs!$Y$36 | ... AA23: =IF(OR((AA$5-Inputs!$V$36+1)<1,(AA$5-Inputs!$V$36+1)>16),0,IF(Inputs!$P$36=5,INDEX(MACRS_5,(AA$5-Inputs!$V$36+1)),INDEX(MACRS_15,(AA$5-Inputs!$V$36+1))))*Inputs!$Y$36
B24: Tax depreciation — Charlie | D24: =SUM(E24:AA24) | E24: =IF(OR((E$5-Inputs!$V$37+1)<1,(E$5-Inputs!$V$37+1)>16),0,IF(Inputs!$P$37=5,INDEX(MACRS_5,(E$5-Inputs!$V$37+1)),INDEX(MACRS_15,(E$5-Inputs!$V$37+1))))*Inputs!$Y$37 | F24: =IF(OR((F$5-Inputs!$V$37+1)<1,(F$5-Inputs!$V$37+1)>16),0,IF(Inputs!$P$37=5,INDEX(MACRS_5,(F$5-Inputs!$V$37+1)),INDEX(MACRS_15,(F$5-Inputs!$V$37+1))))*Inputs!$Y$37 | G24: =IF(OR((G$5-Inputs!$V$37+1)<1,(G$5-Inputs!$V$37+1)>16),0,IF(Inputs!$P$37=5,INDEX(MACRS_5,(G$5-Inputs!$V$37+1)),INDEX(MACRS_15,(G$5-Inputs!$V$37+1))))*Inputs!$Y$37 | H24: =IF(OR((H$5-Inputs!$V$37+1)<1,(H$5-Inputs!$V$37+1)>16),0,IF(Inputs!$P$37=5,INDEX(MACRS_5,(H$5-Inputs!$V$37+1)),INDEX(MACRS_15,(H$5-Inputs!$V$37+1))))*Inputs!$Y$37 | I24: =IF(OR((I$5-Inputs!$V$37+1)<1,(I$5-Inputs!$V$37+1)>16),0,IF(Inputs!$P$37=5,INDEX(MACRS_5,(I$5-Inputs!$V$37+1)),INDEX(MACRS_15,(I$5-Inputs!$V$37+1))))*Inputs!$Y$37 | J24: =IF(OR((J$5-Inputs!$V$37+1)<1,(J$5-Inputs!$V$37+1)>16),0,IF(Inputs!$P$37=5,INDEX(MACRS_5,(J$5-Inputs!$V$37+1)),INDEX(MACRS_15,(J$5-Inputs!$V$37+1))))*Inputs!$Y$37 | K24: =IF(OR((K$5-Inputs!$V$37+1)<1,(K$5-Inputs!$V$37+1)>16),0,IF(Inputs!$P$37=5,INDEX(MACRS_5,(K$5-Inputs!$V$37+1)),INDEX(MACRS_15,(K$5-Inputs!$V$37+1))))*Inputs!$Y$37 | L24: =IF(OR((L$5-Inputs!$V$37+1)<1,(L$5-Inputs!$V$37+1)>16),0,IF(Inputs!$P$37=5,INDEX(MACRS_5,(L$5-Inputs!$V$37+1)),INDEX(MACRS_15,(L$5-Inputs!$V$37+1))))*Inputs!$Y$37 | ... AA24: =IF(OR((AA$5-Inputs!$V$37+1)<1,(AA$5-Inputs!$V$37+1)>16),0,IF(Inputs!$P$37=5,INDEX(MACRS_5,(AA$5-Inputs!$V$37+1)),INDEX(MACRS_15,(AA$5-Inputs!$V$37+1))))*Inputs!$Y$37
B25: Tax depreciation — Delta | D25: =SUM(E25:AA25) | E25: =IF(OR((E$5-Inputs!$V$38+1)<1,(E$5-Inputs!$V$38+1)>16),0,IF(Inputs!$P$38=5,INDEX(MACRS_5,(E$5-Inputs!$V$38+1)),INDEX(MACRS_15,(E$5-Inputs!$V$38+1))))*Inputs!$Y$38 | F25: =IF(OR((F$5-Inputs!$V$38+1)<1,(F$5-Inputs!$V$38+1)>16),0,IF(Inputs!$P$38=5,INDEX(MACRS_5,(F$5-Inputs!$V$38+1)),INDEX(MACRS_15,(F$5-Inputs!$V$38+1))))*Inputs!$Y$38 | G25: =IF(OR((G$5-Inputs!$V$38+1)<1,(G$5-Inputs!$V$38+1)>16),0,IF(Inputs!$P$38=5,INDEX(MACRS_5,(G$5-Inputs!$V$38+1)),INDEX(MACRS_15,(G$5-Inputs!$V$38+1))))*Inputs!$Y$38 | H25: =IF(OR((H$5-Inputs!$V$38+1)<1,(H$5-Inputs!$V$38+1)>16),0,IF(Inputs!$P$38=5,INDEX(MACRS_5,(H$5-Inputs!$V$38+1)),INDEX(MACRS_15,(H$5-Inputs!$V$38+1))))*Inputs!$Y$38 | I25: =IF(OR((I$5-Inputs!$V$38+1)<1,(I$5-Inputs!$V$38+1)>16),0,IF(Inputs!$P$38=5,INDEX(MACRS_5,(I$5-Inputs!$V$38+1)),INDEX(MACRS_15,(I$5-Inputs!$V$38+1))))*Inputs!$Y$38 | J25: =IF(OR((J$5-Inputs!$V$38+1)<1,(J$5-Inputs!$V$38+1)>16),0,IF(Inputs!$P$38=5,INDEX(MACRS_5,(J$5-Inputs!$V$38+1)),INDEX(MACRS_15,(J$5-Inputs!$V$38+1))))*Inputs!$Y$38 | K25: =IF(OR((K$5-Inputs!$V$38+1)<1,(K$5-Inputs!$V$38+1)>16),0,IF(Inputs!$P$38=5,INDEX(MACRS_5,(K$5-Inputs!$V$38+1)),INDEX(MACRS_15,(K$5-Inputs!$V$38+1))))*Inputs!$Y$38 | L25: =IF(OR((L$5-Inputs!$V$38+1)<1,(L$5-Inputs!$V$38+1)>16),0,IF(Inputs!$P$38=5,INDEX(MACRS_5,(L$5-Inputs!$V$38+1)),INDEX(MACRS_15,(L$5-Inputs!$V$38+1))))*Inputs!$Y$38 | ... AA25: =IF(OR((AA$5-Inputs!$V$38+1)<1,(AA$5-Inputs!$V$38+1)>16),0,IF(Inputs!$P$38=5,INDEX(MACRS_5,(AA$5-Inputs!$V$38+1)),INDEX(MACRS_15,(AA$5-Inputs!$V$38+1))))*Inputs!$Y$38
B26: Tax depreciation — Echo | D26: =SUM(E26:AA26) | E26: =IF(OR((E$5-Inputs!$V$39+1)<1,(E$5-Inputs!$V$39+1)>16),0,IF(Inputs!$P$39=5,INDEX(MACRS_5,(E$5-Inputs!$V$39+1)),INDEX(MACRS_15,(E$5-Inputs!$V$39+1))))*Inputs!$Y$39 | F26: =IF(OR((F$5-Inputs!$V$39+1)<1,(F$5-Inputs!$V$39+1)>16),0,IF(Inputs!$P$39=5,INDEX(MACRS_5,(F$5-Inputs!$V$39+1)),INDEX(MACRS_15,(F$5-Inputs!$V$39+1))))*Inputs!$Y$39 | G26: =IF(OR((G$5-Inputs!$V$39+1)<1,(G$5-Inputs!$V$39+1)>16),0,IF(Inputs!$P$39=5,INDEX(MACRS_5,(G$5-Inputs!$V$39+1)),INDEX(MACRS_15,(G$5-Inputs!$V$39+1))))*Inputs!$Y$39 | H26: =IF(OR((H$5-Inputs!$V$39+1)<1,(H$5-Inputs!$V$39+1)>16),0,IF(Inputs!$P$39=5,INDEX(MACRS_5,(H$5-Inputs!$V$39+1)),INDEX(MACRS_15,(H$5-Inputs!$V$39+1))))*Inputs!$Y$39 | I26: =IF(OR((I$5-Inputs!$V$39+1)<1,(I$5-Inputs!$V$39+1)>16),0,IF(Inputs!$P$39=5,INDEX(MACRS_5,(I$5-Inputs!$V$39+1)),INDEX(MACRS_15,(I$5-Inputs!$V$39+1))))*Inputs!$Y$39 | J26: =IF(OR((J$5-Inputs!$V$39+1)<1,(J$5-Inputs!$V$39+1)>16),0,IF(Inputs!$P$39=5,INDEX(MACRS_5,(J$5-Inputs!$V$39+1)),INDEX(MACRS_15,(J$5-Inputs!$V$39+1))))*Inputs!$Y$39 | K26: =IF(OR((K$5-Inputs!$V$39+1)<1,(K$5-Inputs!$V$39+1)>16),0,IF(Inputs!$P$39=5,INDEX(MACRS_5,(K$5-Inputs!$V$39+1)),INDEX(MACRS_15,(K$5-Inputs!$V$39+1))))*Inputs!$Y$39 | L26: =IF(OR((L$5-Inputs!$V$39+1)<1,(L$5-Inputs!$V$39+1)>16),0,IF(Inputs!$P$39=5,INDEX(MACRS_5,(L$5-Inputs!$V$39+1)),INDEX(MACRS_15,(L$5-Inputs!$V$39+1))))*Inputs!$Y$39 | ... AA26: =IF(OR((AA$5-Inputs!$V$39+1)<1,(AA$5-Inputs!$V$39+1)>16),0,IF(Inputs!$P$39=5,INDEX(MACRS_5,(AA$5-Inputs!$V$39+1)),INDEX(MACRS_15,(AA$5-Inputs!$V$39+1))))*Inputs!$Y$39
B27: Total tax depreciation | D27: =SUM(E27:AA27) | E27: =SUM(E22:E26) | F27: =SUM(F22:F26) | G27: =SUM(G22:G26) | H27: =SUM(H22:H26) | I27: =SUM(I22:I26) | J27: =SUM(J22:J26) | K27: =SUM(K22:K26) | L27: =SUM(L22:L26) | ... AA27: =SUM(AA22:AA26)
B29: Debt sizing (sculpted to target DSCR, drawn at term conversion)
B30: Term conversion year (latest live COD) | C30: =MAX(Inputs!$V$35:$V$39)
B31: Senior rate (live) | C31: =SrRateBase+RateAdj/10000
B32: Mezzanine rate (live) | C32: =MzRateBase+RateAdj/10000
B34: Years from conversion | E34: =E$5-ConvYear | F34: =F$5-ConvYear | G34: =G$5-ConvYear | H34: =H$5-ConvYear | I34: =I$5-ConvYear | J34: =J$5-ConvYear | K34: =K$5-ConvYear | L34: =L$5-ConvYear | ... AA34: =AA$5-ConvYear
B35: Debt service period flag | E35: =IF(AND(E34>=1,E34<=Tenor),1,0) | F35: =IF(AND(F34>=1,F34<=Tenor),1,0) | G35: =IF(AND(G34>=1,G34<=Tenor),1,0) | H35: =IF(AND(H34>=1,H34<=Tenor),1,0) | I35: =IF(AND(I34>=1,I34<=Tenor),1,0) | J35: =IF(AND(J34>=1,J34<=Tenor),1,0) | K35: =IF(AND(K34>=1,K34<=Tenor),1,0) | L35: =IF(AND(L34>=1,L34<=Tenor),1,0) | ... AA35: =IF(AND(AA34>=1,AA34<=Tenor),1,0)
B36: CFADS available for debt service | D36: =SUM(E36:AA36) | E36: =E35*E16 | F36: =F35*F16 | G36: =G35*G16 | H36: =H35*H16 | I36: =I35*I16 | J36: =J35*J16 | K36: =K35*K16 | L36: =L35*L16 | ... AA36: =AA35*AA16
B38: Senior debt
B39: Debt service at target DSCR (uncapped) | D39: =SUM(E39:AA39) | E39: =E36/SrDSCR | F39: =F36/SrDSCR | G39: =G36/SrDSCR | H39: =H36/SrDSCR | I39: =I36/SrDSCR | J39: =J36/SrDSCR | K39: =K36/SrDSCR | L39: =L36/SrDSCR | ... AA39: =AA36/SrDSCR
B40: Discount factor at senior rate | E40: =IF(E35=1,1/(1+SrRate)^E34,0) | F40: =IF(F35=1,1/(1+SrRate)^F34,0) | G40: =IF(G35=1,1/(1+SrRate)^G34,0) | H40: =IF(H35=1,1/(1+SrRate)^H34,0) | I40: =IF(I35=1,1/(1+SrRate)^I34,0) | J40: =IF(J35=1,1/(1+SrRate)^J34,0) | K40: =IF(K35=1,1/(1+SrRate)^K34,0) | L40: =IF(L35=1,1/(1+SrRate)^L34,0) | ... AA40: =IF(AA35=1,1/(1+SrRate)^AA34,0)
B41: Debt capacity from sculpting (PV of DS) | C41: =SUMPRODUCT(E39:AA39,E40:AA40)
B42: Gearing cap (senior max gearing × capex) | C42: =SrMaxGear*TotalCapex
B43: Senior debt amount | C43: =MIN(C41,C42) | D43: =IF(C42<C41,"gearing-capped","DSCR-sized")
B44: Senior debt service | D44: =SUM(E44:AA44) | E44: =IF(C41=0,0,E39*SrAmt/$C$41) | F44: =IF(C41=0,0,F39*SrAmt/$C$41) | G44: =IF(C41=0,0,G39*SrAmt/$C$41) | H44: =IF(C41=0,0,H39*SrAmt/$C$41) | I44: =IF(C41=0,0,I39*SrAmt/$C$41) | J44: =IF(C41=0,0,J39*SrAmt/$C$41) | K44: =IF(C41=0,0,K39*SrAmt/$C$41) | L44: =IF(C41=0,0,L39*SrAmt/$C$41) | M44: =IF(C41=0,0,M39*SrAmt/$C$41) | N44: =IF(C41=0,0,N39*SrAmt/$C$41) | O44: =IF(C41=0,0,O39*SrAmt/$C$41) | P44: =IF(C41=0,0,P39*SrAmt/$C$41) | Q44: =IF(C41=0,0,Q39*SrAmt/$C$41) | R44: =IF(C41=0,0,R39*SrAmt/$C$41) | S44: =IF(C41=0,0,S39*SrAmt/$C$41) | T44: =IF(C41=0,0,T39*SrAmt/$C$41) | U44: =IF(C41=0,0,U39*SrAmt/$C$41) | V44: =IF(C41=0,0,V39*SrAmt/$C$41) | W44: =IF(C41=0,0,W39*SrAmt/$C$41) | X44: =IF(C41=0,0,X39*SrAmt/$C$41) | Y44: =IF(C41=0,0,Y39*SrAmt/$C$41) | Z44: =IF(C41=0,0,Z39*SrAmt/$C$41) | AA44: =IF(C41=0,0,AA39*SrAmt/$C$41)
B45: Opening balance | E45: =0 | F45: =E49 | G45: =F49 | H45: =G49 | I45: =H49 | J45: =I49 | K45: =J49 | L45: =K49 | M45: =L49 | ... AA45: =Z49
B46: Drawdown | D46: =SUM(E46:AA46) | E46: =IF(E$5=ConvYear,SrAmt,0) | F46: =IF(F$5=ConvYear,SrAmt,0) | G46: =IF(G$5=ConvYear,SrAmt,0) | H46: =IF(H$5=ConvYear,SrAmt,0) | I46: =IF(I$5=ConvYear,SrAmt,0) | J46: =IF(J$5=ConvYear,SrAmt,0) | K46: =IF(K$5=ConvYear,SrAmt,0) | L46: =IF(L$5=ConvYear,SrAmt,0) | ... AA46: =IF(AA$5=ConvYear,SrAmt,0)
B47: Interest | D47: =SUM(E47:AA47) | E47: =E45*SrRate | F47: =F45*SrRate | G47: =G45*SrRate | H47: =H45*SrRate | I47: =I45*SrRate | J47: =J45*SrRate | K47: =K45*SrRate | L47: =L45*SrRate | ... AA47: =AA45*SrRate
B48: Principal repayment | D48: =SUM(E48:AA48) | E48: =E44-E47 | F48: =F44-F47 | G48: =G44-G47 | H48: =H44-H47 | I48: =I44-I47 | J48: =J44-J47 | K48: =K44-K47 | L48: =L44-L47 | ... AA48: =AA44-AA47
B49: Closing balance | E49: =E45+E46-E48 | F49: =F45+F46-F48 | G49: =G45+G46-G48 | H49: =H45+H46-H48 | I49: =I45+I46-I48 | J49: =J45+J46-J48 | K49: =K45+K46-K48 | L49: =L45+L46-L48 | ... AA49: =AA45+AA46-AA48
B51: Mezzanine debt
B52: Debt service to combined DSCR, less senior (uncapped) | D52: =SUM(E52:AA52) | E52: =E36/CombDSCR-E44 | F52: =F36/CombDSCR-F44 | G52: =G36/CombDSCR-G44 | H52: =H36/CombDSCR-H44 | I52: =I36/CombDSCR-I44 | J52: =J36/CombDSCR-J44 | K52: =K36/CombDSCR-K44 | L52: =L36/CombDSCR-L44 | ... AA52: =AA36/CombDSCR-AA44
B53: Discount factor at mezzanine rate | E53: =IF(E35=1,1/(1+MzRate)^E34,0) | F53: =IF(F35=1,1/(1+MzRate)^F34,0) | G53: =IF(G35=1,1/(1+MzRate)^G34,0) | H53: =IF(H35=1,1/(1+MzRate)^H34,0) | I53: =IF(I35=1,1/(1+MzRate)^I34,0) | J53: =IF(J35=1,1/(1+MzRate)^J34,0) | K53: =IF(K35=1,1/(1+MzRate)^K34,0) | L53: =IF(L35=1,1/(1+MzRate)^L34,0) | ... AA53: =IF(AA35=1,1/(1+MzRate)^AA34,0)
B54: Debt capacity from sculpting (PV of DS) | C54: =SUMPRODUCT(E52:AA52,E53:AA53)
B55: Room under total gearing cap | C55: =TotMaxGear*TotalCapex-SrAmt
B56: Mezzanine debt amount | C56: =MAX(0,MIN(C54,C55))
B57: Mezzanine debt service | D57: =SUM(E57:AA57) | E57: =IF($C$54<=0,0,E52*MzAmt/$C$54) | F57: =IF($C$54<=0,0,F52*MzAmt/$C$54) | G57: =IF($C$54<=0,0,G52*MzAmt/$C$54) | H57: =IF($C$54<=0,0,H52*MzAmt/$C$54) | I57: =IF($C$54<=0,0,I52*MzAmt/$C$54) | J57: =IF($C$54<=0,0,J52*MzAmt/$C$54) | K57: =IF($C$54<=0,0,K52*MzAmt/$C$54) | L57: =IF($C$54<=0,0,L52*MzAmt/$C$54) | ... AA57: =IF($C$54<=0,0,AA52*MzAmt/$C$54)
B58: Opening balance | E58: =0 | F58: =E62 | G58: =F62 | H58: =G62 | I58: =H62 | J58: =I62 | K58: =J62 | L58: =K62 | M58: =L62 | ... AA58: =Z62
B59: Drawdown | D59: =SUM(E59:AA59) | E59: =IF(E$5=ConvYear,MzAmt,0) | F59: =IF(F$5=ConvYear,MzAmt,0) | G59: =IF(G$5=ConvYear,MzAmt,0) | H59: =IF(H$5=ConvYear,MzAmt,0) | I59: =IF(I$5=ConvYear,MzAmt,0) | J59: =IF(J$5=ConvYear,MzAmt,0) | K59: =IF(K$5=ConvYear,MzAmt,0) | L59: =IF(L$5=ConvYear,MzAmt,0) | ... AA59: =IF(AA$5=ConvYear,MzAmt,0)
B60: Interest | D60: =SUM(E60:AA60) | E60: =E58*MzRate | F60: =F58*MzRate | G60: =G58*MzRate | H60: =H58*MzRate | I60: =I58*MzRate | J60: =J58*MzRate | K60: =K58*MzRate | L60: =L58*MzRate | ... AA60: =AA58*MzRate
B61: Principal repayment | D61: =SUM(E61:AA61) | E61: =E57-E60 | F61: =F57-F60 | G61: =G57-G60 | H61: =H57-H60 | I61: =I57-I60 | J61: =J57-J60 | K61: =K57-K60 | L61: =L57-L60 | ... AA61: =AA57-AA60
B62: Closing balance | E62: =E58+E59-E61 | F62: =F58+F59-F61 | G62: =G58+G59-G61 | H62: =H58+H59-H61 | I62: =I58+I59-I61 | J62: =J58+J59-J61 | K62: =K58+K59-K61 | L62: =L58+L59-L61 | ... AA62: =AA58+AA59-AA61
B64: Upfront financing fees | D64: =SUM(E64:AA64) | E64: =IF(E$5=ConvYear,SrAmt*SrFee+MzAmt*MzFee,0) | F64: =IF(F$5=ConvYear,SrAmt*SrFee+MzAmt*MzFee,0) | G64: =IF(G$5=ConvYear,SrAmt*SrFee+MzAmt*MzFee,0) | H64: =IF(H$5=ConvYear,SrAmt*SrFee+MzAmt*MzFee,0) | I64: =IF(I$5=ConvYear,SrAmt*SrFee+MzAmt*MzFee,0) | J64: =IF(J$5=ConvYear,SrAmt*SrFee+MzAmt*MzFee,0) | K64: =IF(K$5=ConvYear,SrAmt*SrFee+MzAmt*MzFee,0) | L64: =IF(L$5=ConvYear,SrAmt*SrFee+MzAmt*MzFee,0) | ... AA64: =IF(AA$5=ConvYear,SrAmt*SrFee+MzAmt*MzFee,0)
B65: Senior DSCR | E65: =IF(E35=1,E36/E44,"") | F65: =IF(F35=1,F36/F44,"") | G65: =IF(G35=1,G36/G44,"") | H65: =IF(H35=1,H36/H44,"") | I65: =IF(I35=1,I36/I44,"") | J65: =IF(J35=1,J36/J44,"") | K65: =IF(K35=1,K36/K44,"") | L65: =IF(L35=1,L36/L44,"") | ... AA65: =IF(AA35=1,AA36/AA44,"")
B66: Combined DSCR | E66: =IF(E35=1,E36/(E44+E57),"") | F66: =IF(F35=1,F36/(F44+F57),"") | G66: =IF(G35=1,G36/(G44+G57),"") | H66: =IF(H35=1,H36/(H44+H57),"") | I66: =IF(I35=1,I36/(I44+I57),"") | J66: =IF(J35=1,J36/(J44+J57),"") | K66: =IF(K35=1,K36/(K44+K57),"") | L66: =IF(L35=1,L36/(L44+L57),"") | ... AA66: =IF(AA35=1,AA36/(AA44+AA57),"")
B68: Income tax
B69: Taxable income (EBITDA − interest − tax depreciation) | D69: =SUM(E69:AA69) | E69: =E16-E47-E60-E27 | F69: =F16-F47-F60-F27 | G69: =G16-G47-G60-G27 | H69: =H16-H47-H60-H27 | I69: =I16-I47-I60-I27 | J69: =J16-J47-J60-J27 | K69: =K16-K47-K60-K27 | L69: =L16-L47-L60-L27 | ... AA69: =AA16-AA47-AA60-AA27
B70: Income tax (negative = benefit to sponsor) | D70: =SUM(E70:AA70) | E70: =E69*TaxRate | F70: =F69*TaxRate | G70: =G69*TaxRate | H70: =H69*TaxRate | I70: =I69*TaxRate | J70: =J69*TaxRate | K70: =K69*TaxRate | L70: =L69*TaxRate | ... AA70: =AA69*TaxRate
B71: Unlevered income tax (for project IRR) | D71: =SUM(E71:AA71) | E71: =(E16-E27)*TaxRate | F71: =(F16-F27)*TaxRate | G71: =(G16-G27)*TaxRate | H71: =(H16-H27)*TaxRate | I71: =(I16-I27)*TaxRate | J71: =(J16-J27)*TaxRate | K71: =(K16-K27)*TaxRate | L71: =(L16-L27)*TaxRate | ... AA71: =(AA16-AA27)*TaxRate
B73: Cash flows & returns
B74: Project (unlevered, after-tax) cash flow | D74: =SUM(E74:AA74) | E74: =-E20+E16-E71+E21 | F74: =-F20+F16-F71+F21 | G74: =-G20+G16-G71+G21 | H74: =-H20+H16-H71+H21 | I74: =-I20+I16-I71+I21 | J74: =-J20+J16-J71+J21 | K74: =-K20+K16-K71+K21 | L74: =-L20+L16-L71+L21 | ... AA74: =-AA20+AA16-AA71+AA21
B75: Equity (levered, after-tax) cash flow | D75: =SUM(E75:AA75) | E75: =-E20+E46+E59-E64+E16-E44-E57-E70+E21 | F75: =-F20+F46+F59-F64+F16-F44-F57-F70+F21 | G75: =-G20+G46+G59-G64+G16-G44-G57-G70+G21 | H75: =-H20+H46+H59-H64+H16-H44-H57-H70+H21 | I75: =-I20+I46+I59-I64+I16-I44-I57-I70+I21 | J75: =-J20+J46+J59-J64+J16-J44-J57-J70+J21 | K75: =-K20+K46+K59-K64+K16-K44-K57-K70+K21 | L75: =-L20+L46+L59-L64+L16-L44-L57-L70+L21 | ... AA75: =-AA20+AA46+AA59-AA64+AA16-AA44-AA57-AA70+AA21
B76: Cumulative equity cash flow | E76: =E75 | F76: =E76+F75 | G76: =F76+G75 | H76: =G76+H75 | I76: =H76+I75 | J76: =I76+J75 | K76: =J76+K75 | L76: =K76+L75 | M76: =L76+M75 | ... AA76: =Z76+AA75

Sheet Assumption Log
B2: Assumption Log
B3: Every input, who owns it, the basis used, and what to validate it against. Values link live to Inputs.
B5: ID | C5: Category | D5: Assumption | E5: Value | F5: Unit | G5: Owner (source team) | H5: Basis / rationale | I5: Validate against | J5: Status
B6: A-01 | C6: Revenue | D6: Capacity price (2027 $) | E6: =CapPrice | F6: $/kW-month | G6: Commercial | H6: Illustrative 2027 capacity price, set near the level that clears the target return | I6: Recent ISO/RTO capacity auction results (e.g. PJM BRA, NYISO ICAP, ISO-NE FCA) and bilateral RA contract quotes | J6: Illustrative — to validate
B7: A-02 | C7: Revenue | D7: Capacity price & margin escalation | E7: =PriceEsc | F7: % / yr | G7: Commercial | H7: Roughly inflation-linked | I7: Contract escalators in RA/capacity agreements; forward curves | J7: Illustrative — to validate
B8: A-03 | C8: Opex | D8: O&M, lease & G&A escalation | E8: =OMEsc | F8: % / yr | G8: Asset Management | H8: Slightly above CPI for labor-heavy O&M | I8: O&M / LTSA contract escalators | J8: Illustrative — to validate
B9: A-04 | C9: Capex | D9: Owner's costs & contingency | E9: =Contingency | F9: % of EPC | G9: Engineering / EPC | H9: Owner's costs, interconnection true-ups and contingency | I9: EPC bid spread; interconnection study cost estimates | J9: Illustrative — to validate
B10: A-05 | C10: Opex | D10: Insurance | E10: =Insurance | F10: % capex / yr | G10: Risk / Insurance | H10: Typical % of replacement cost for BESS | I10: Broker indications | J10: Illustrative — to validate
B11: A-06 | C11: Opex | D11: Property tax | E11: =PropTax | F11: % capex / yr | G11: Tax | H11: Varies by jurisdiction and abatements | I11: County assessor / PILOT agreements | J11: Illustrative — to validate
B12: A-07 | C12: Opex | D12: Portfolio G&A and asset management | E12: =GACost | F12: $k / yr | G12: Finance | H12: Portfolio-level asset management and corporate overhead | I12: Internal budget | J12: Illustrative — to validate
B13: A-08 | C13: Tax | D13: Blended income tax rate | E13: =TaxRate | F13: % | G13: Tax | H13: 21% federal + ~5% blended state | I13: Tax department; state apportionment | J13: Illustrative — to validate
B14: A-09 | C14: Tax | D14: Investment tax credit (storage only) | E14: =ITCRate | F14: % eligible capex | G14: Tax | H14: 30% base credit assuming prevailing wage & apprenticeship; no adders | I14: Current §48E rules incl. any phase-down and FEOC restrictions | J14: Illustrative — to validate
B15: A-10 | C15: Tax | D15: ITC transfer price | E15: =ITCTransfer | F15: $ per $1 credit | G15: Tax / Treasury | H15: Credit sold to a third party under transferability | I15: Recent transfer market quotes from advisors / brokers | J15: Illustrative — to validate
B16: A-11 | C16: Tax | D16: Depreciable basis reduction | E16: =ITCBasisRed | F16: % of ITC | G16: Tax | H16: Basis reduced by 50% of ITC | I16: Tax counsel | J16: Illustrative — to validate
B17: A-12 | C17: Financing | D17: Senior debt interest rate | E17: =SrRateBase | F17: % / yr | G17: Treasury / Capital Markets | H17: Base rate + margin for contracted storage debt | I17: Lender term sheets; SOFR swap curve | J17: Illustrative — to validate
B18: A-13 | C18: Financing | D18: Senior target DSCR | E18: =SrDSCR | F18: x | G18: Treasury / Capital Markets | H18: Contracted capacity revenue supports a mid-1.3x DSCR | I18: Lender term sheets / rating agency criteria | J18: Illustrative — to validate
B19: A-14 | C19: Financing | D19: Senior max gearing | E19: =SrMaxGear | F19: % of capex | G19: Treasury / Capital Markets | H19: Typical leverage ceiling | I19: Lender term sheets | J19: Illustrative — to validate
B20: A-15 | C20: Financing | D20: Senior upfront fee | E20: =SrFee | F20: % of amount | G20: Treasury / Capital Markets | H20: Arrangement fee | I20: Lender term sheets | J20: Illustrative — to validate
B21: A-16 | C21: Financing | D21: Mezzanine interest rate | E21: =MzRateBase | F21: % / yr | G21: Treasury / Capital Markets | H21: Subordinated / holdco debt pricing | I21: Mezz lender indications | J21: Illustrative — to validate
B22: A-17 | C22: Financing | D22: Combined (senior + mezz) target DSCR | E22: =CombDSCR | F22: x | G22: Treasury / Capital Markets | H22: Mezz sized to the gap between senior and combined DSCR | I22: Mezz lender indications | J22: Illustrative — to validate
B23: A-18 | C23: Financing | D23: Total max gearing | E23: =TotMaxGear | F23: % of capex | G23: Treasury / Capital Markets | H23: Total leverage ceiling | I23: Lender term sheets | J23: Illustrative — to validate
B24: A-19 | C24: Financing | D24: Mezzanine upfront fee | E24: =MzFee | F24: % of amount | G24: Treasury / Capital Markets | H24: Arrangement fee | I24: Mezz lender indications | J24: Illustrative — to validate
B25: A-20 | C25: Financing | D25: Debt tenor (both tranches) | E25: =Tenor | F25: years | G25: Treasury / Capital Markets | H25: Shorter than 20-year asset life | I25: Lender term sheets; contract tenor | J25: Illustrative — to validate
B26: A-21 | C26: Returns | D26: Cost of equity / target equity IRR | E26: =CostEquity | F26: % | G26: Investment Committee | H26: Sponsor hurdle for contracted storage | I26: IC hurdle rates; comparable transactions | J26: Illustrative — to validate
B27: A-22 | C27: Capex | D27: Alpha — EPC unit cost | E27: =Inputs!F35 | F27: $/kWh | G27: Engineering / EPC | H27: All-in EPC for 4h/2h storage and recip engine backup generation | I27: EPC bids; NREL Annual Technology Baseline; Lazard LCOE+/LCOS | J27: Illustrative — to validate
B28: A-23 | C28: Capex | D28: Bravo — EPC unit cost | E28: =Inputs!F36 | F28: $/kWh | G28: Engineering / EPC | H28: All-in EPC for 4h/2h storage and recip engine backup generation | I28: EPC bids; NREL Annual Technology Baseline; Lazard LCOE+/LCOS | J28: Illustrative — to validate
B29: A-24 | C29: Capex | D29: Charlie — EPC unit cost | E29: =Inputs!F37 | F29: $/kWh | G29: Engineering / EPC | H29: All-in EPC for 4h/2h storage and recip engine backup generation | I29: EPC bids; NREL Annual Technology Baseline; Lazard LCOE+/LCOS | J29: Illustrative — to validate
B30: A-25 | C30: Capex | D30: Delta — EPC unit cost | E30: =Inputs!F38 | F30: $/kWh | G30: Engineering / EPC | H30: All-in EPC for 4h/2h storage and recip engine backup generation | I30: EPC bids; NREL Annual Technology Baseline; Lazard LCOE+/LCOS | J30: Illustrative — to validate
B31: A-26 | C31: Capex | D31: Echo — EPC unit cost | E31: =Inputs!F39 | F31: $/kW | G31: Engineering / EPC | H31: All-in EPC for 4h/2h storage and recip engine backup generation | I31: EPC bids; NREL Annual Technology Baseline; Lazard LCOE+/LCOS | J31: Illustrative — to validate
B32: A-27 | C32: Timing | D32: Alpha — COD (base) | E32: =Inputs!I35 | F32: date | G32: Development / Construction | H32: Staggered CODs Dec-27 to Jul-28 | I32: Interconnection agreements; EPC schedule | J32: Illustrative — to validate
B33: A-28 | C33: Timing | D33: Bravo — COD (base) | E33: =Inputs!I36 | F33: date | G33: Development / Construction | H33: Staggered CODs Dec-27 to Jul-28 | I33: Interconnection agreements; EPC schedule | J33: Illustrative — to validate
B34: A-29 | C34: Timing | D34: Charlie — COD (base) | E34: =Inputs!I37 | F34: date | G34: Development / Construction | H34: Staggered CODs Dec-27 to Jul-28 | I34: Interconnection agreements; EPC schedule | J34: Illustrative — to validate
B35: A-30 | C35: Timing | D35: Delta — COD (base) | E35: =Inputs!I38 | F35: date | G35: Development / Construction | H35: Staggered CODs Dec-27 to Jul-28 | I35: Interconnection agreements; EPC schedule | J35: Illustrative — to validate
B36: A-31 | C36: Timing | D36: Echo — COD (base) | E36: =Inputs!I39 | F36: date | G36: Development / Construction | H36: Staggered CODs Dec-27 to Jul-28 | I36: Interconnection agreements; EPC schedule | J36: Illustrative — to validate
B37: A-32 | C37: Revenue | D37: Alpha — Capacity accreditation | E37: =Inputs!J35 | F37: % | G37: Commercial | H37: Effective load carrying capability by duration | I37: ISO accreditation (ELCC) tables | J37: Illustrative — to validate
B38: A-33 | C38: Revenue | D38: Bravo — Capacity accreditation | E38: =Inputs!J36 | F38: % | G38: Commercial | H38: Effective load carrying capability by duration | I38: ISO accreditation (ELCC) tables | J38: Illustrative — to validate
B39: A-34 | C39: Revenue | D39: Charlie — Capacity accreditation | E39: =Inputs!J37 | F39: % | G39: Commercial | H39: Effective load carrying capability by duration | I39: ISO accreditation (ELCC) tables | J39: Illustrative — to validate
B40: A-35 | C40: Revenue | D40: Delta — Capacity accreditation | E40: =Inputs!J38 | F40: % | G40: Commercial | H40: Effective load carrying capability by duration | I40: ISO accreditation (ELCC) tables | J40: Illustrative — to validate
B41: A-36 | C41: Revenue | D41: Echo — Capacity accreditation | E41: =Inputs!J39 | F41: % | G41: Commercial | H41: Effective load carrying capability by duration | I41: ISO accreditation (ELCC) tables | J41: Illustrative — to validate
B42: A-37 | C42: Operations | D42: Alpha — Degradation / yr | E42: =Inputs!K35 | F42: % / yr | G42: Engineering / OEM | H42: No augmentation assumed, so accredited MW falls each year | I42: OEM warranty curves | J42: Illustrative — to validate
B43: A-38 | C43: Operations | D43: Bravo — Degradation / yr | E43: =Inputs!K36 | F43: % / yr | G43: Engineering / OEM | H43: No augmentation assumed, so accredited MW falls each year | I43: OEM warranty curves | J43: Illustrative — to validate
B44: A-39 | C44: Operations | D44: Charlie — Degradation / yr | E44: =Inputs!K37 | F44: % / yr | G44: Engineering / OEM | H44: No augmentation assumed, so accredited MW falls each year | I44: OEM warranty curves | J44: Illustrative — to validate
B45: A-40 | C45: Operations | D45: Delta — Degradation / yr | E45: =Inputs!K38 | F45: % / yr | G45: Engineering / OEM | H45: No augmentation assumed, so accredited MW falls each year | I45: OEM warranty curves | J45: Illustrative — to validate
B46: A-41 | C46: Operations | D46: Echo — Degradation / yr | E46: =Inputs!K39 | F46: % / yr | G46: Engineering / OEM | H46: No augmentation assumed, so accredited MW falls each year | I46: OEM warranty curves | J46: Illustrative — to validate
B47: A-42 | C47: Opex | D47: Alpha — Fixed O&M $/kW-yr | E47: =Inputs!L35 | F47: $/kW-yr | G47: Asset Management | H47: Includes LTSA and warranty extension | I47: O&M / LTSA quotes | J47: Illustrative — to validate
B48: A-43 | C48: Opex | D48: Bravo — Fixed O&M $/kW-yr | E48: =Inputs!L36 | F48: $/kW-yr | G48: Asset Management | H48: Includes LTSA and warranty extension | I48: O&M / LTSA quotes | J48: Illustrative — to validate
B49: A-44 | C49: Opex | D49: Charlie — Fixed O&M $/kW-yr | E49: =Inputs!L37 | F49: $/kW-yr | G49: Asset Management | H49: Includes LTSA and warranty extension | I49: O&M / LTSA quotes | J49: Illustrative — to validate
B50: A-45 | C50: Opex | D50: Delta — Fixed O&M $/kW-yr | E50: =Inputs!L38 | F50: $/kW-yr | G50: Asset Management | H50: Includes LTSA and warranty extension | I50: O&M / LTSA quotes | J50: Illustrative — to validate
B51: A-46 | C51: Opex | D51: Echo — Fixed O&M $/kW-yr | E51: =Inputs!L39 | F51: $/kW-yr | G51: Asset Management | H51: Includes LTSA and warranty extension | I51: O&M / LTSA quotes | J51: Illustrative — to validate
B52: A-47 | C52: Revenue | D52: Alpha — Energy & ancillary margin $/kW-yr | E52: =Inputs!M35 | F52: $/kW-yr | G52: Commercial / Trading | H52: Conservative merchant upside on top of capacity | I52: Historical arbitrage & AS spreads by node | J52: Illustrative — to validate
B53: A-48 | C53: Revenue | D53: Bravo — Energy & ancillary margin $/kW-yr | E53: =Inputs!M36 | F53: $/kW-yr | G53: Commercial / Trading | H53: Conservative merchant upside on top of capacity | I53: Historical arbitrage & AS spreads by node | J53: Illustrative — to validate
B54: A-49 | C54: Revenue | D54: Charlie — Energy & ancillary margin $/kW-yr | E54: =Inputs!M37 | F54: $/kW-yr | G54: Commercial / Trading | H54: Conservative merchant upside on top of capacity | I54: Historical arbitrage & AS spreads by node | J54: Illustrative — to validate
B55: A-50 | C55: Revenue | D55: Delta — Energy & ancillary margin $/kW-yr | E55: =Inputs!M38 | F55: $/kW-yr | G55: Commercial / Trading | H55: Conservative merchant upside on top of capacity | I55: Historical arbitrage & AS spreads by node | J55: Illustrative — to validate
B56: A-51 | C56: Revenue | D56: Echo — Energy & ancillary margin $/kW-yr | E56: =Inputs!M39 | F56: $/kW-yr | G56: Commercial / Trading | H56: Conservative merchant upside on top of capacity | I56: Historical arbitrage & AS spreads by node | J56: Illustrative — to validate

Sheet Checks
B2: Model Checks
B3: Integrity checks; all must be TRUE. The overall flag feeds the Summary sheet.
B4: ALL CHECKS PASS | C4: =AND(C7:C19)
B6: Check | C6: Pass? | D6: Value
B7: Senior debt fully repaid by end of tenor | C7: =ABS(Annual!AA49)<0.01 | D7: =Annual!AA49
B8: Mezzanine debt fully repaid by end of tenor | C8: =ABS(Annual!AA62)<0.01 | D8: =Annual!AA62
B9: Min senior DSCR ≥ target | C9: =MinDSCRSr>=SrDSCR-0.0001 | D9: =MinDSCRSr
B10: Min combined DSCR ≥ target | C10: =MinDSCRComb>=CombDSCR-0.0001 | D10: =MinDSCRComb
B11: Sources = uses | C11: =ABS(Summary!F12-Summary!F13)<0.01 | D11: =Summary!F12-Summary!F13
B12: Monthly capex = asset capex on Inputs | C12: =ABS(Monthly!D78-TotalCapexInputs)<0.01 | D12: =Monthly!D78-TotalCapexInputs
B13: Annual revenue = monthly revenue | C13: =ABS(Annual!D10-Monthly!D71)<0.01 | D13: =Annual!D10-Monthly!D71
B14: Annual EBITDA = monthly EBITDA | C14: =ABS(Annual!D16-Monthly!D77)<0.01 | D14: =Annual!D16-Monthly!D77
B15: Total gearing ≤ cap | C15: =Gearing<=TotMaxGear+0.0001 | D15: =Gearing
B16: Construction starts on/after model start | C16: =MIN(Inputs!W35:W39)>=ModelStart | D16: =MIN(Inputs!W35:W39)
B17: All asset lives end within model horizon | C17: =MAX(Inputs!Z35:Z39)<=EDATE(ModelStart,276) | D17: =MAX(Inputs!Z35:Z39)
B18: Tax depreciation = depreciable basis | C18: =ABS(Annual!D27-Inputs!Y40)<0.01 | D18: =Annual!D27-Inputs!Y40
B19: Scenario selector is 1, 2 or 3 | C19: =OR(ScenarioSel=1,ScenarioSel=2,ScenarioSel=3) | D19: =ScenarioSel
